{"comments": [{"audioMultiplier": 1.0, "autoMode": 0, "avatarID": "umr4014", "avatarName": "흐에매그", "band": 1003, "commentID": "13fd2dc86d7c72e56c5b91f8cd7d5d6aba92288ea2eb6525bb5e50026974aa3e42a2b92d2cf6141151fc517f786e523dbf6a4d3321551105c74c0438cce8babf", "commentary": "", "date": "2025-08-27T03:02:38", "faintNoteMode": 0, "handled": 8, "hitPointsMode": 5, "inputFavorMode": 0, "inputFlags": 1, "isBand1": true, "isF": false, "isPaused": false, "judgmentMode": 1, "longNoteMode": 0, "lowestJudgmentConditionMode": 0, "multiplier": 10.404624277456648, "noteMobilityMode": 0, "noteModifyMode": 0, "noteSaltMode": 0, "point": 1.0, "salt": 380053953, "stand": 999002}, {"audioMultiplier": 1.0, "autoMode": 0, "avatarID": "cococd", "avatarName": "EMPRESS", "band": 1003, "commentID": "6bd108fa087cdd4df772a5086b37e6575fc6f205bb0c8cc23dd54a1f333088f27fe3a2d614d0ed7b19e5032d9ee8d6fc1d69081e44d64ba57ffab3e1420c0b30", "commentary": "", "date": "2026-03-27T14:19:33", "faintNoteMode": 0, "handled": 8, "hitPointsMode": 5, "inputFavorMode": 0, "inputFlags": 1, "isBand1": true, "isF": false, "isPaused": false, "judgmentMode": 1, "longNoteMode": 0, "lowestJudgmentConditionMode": 0, "multiplier": 8.786127167630058, "noteMobilityMode": 0, "noteModifyMode": 0, "noteSaltMode": 0, "point": 1.0, "salt": 755687, "stand": 997906}, {"audioMultiplier": 1.0, "autoMode": 0, "avatarID": "skaks135", "avatarName": "햄꾸", "band": 1003, "commentID": "0c8c4073c9ddd5d0e7a31f8db710b2c932f4025be2b7e74ddd02afd542b4063909b8455ebd5124825e7e1be52d54a60b7e006e7052e4a9532d0e8a0b0a624f4f", "commentary": "", "date": "2025-08-21T15:33:17", "faintNoteMode": 0, "handled": 8, "hitPointsMode": 8, "inputFavorMode": 0, "inputFlags": 1, "isBand1": true, "isF": false, "isPaused": false, "judgmentMode": 1, "longNoteMode": 0, "lowestJudgmentConditionMode": 0, "multiplier": 11.098265895953757, "noteMobilityMode": 0, "noteModifyMode": 0, "noteSaltMode": 0, "point": 1.0, "salt": 53421000, "stand": 997407}, {"audioMultiplier": 1.0, "autoMode": 0, "avatarID": "나노응애", "avatarName": "나노응애", "band": 1003, "commentID": "50bcf769c39864ab7453833d2c7a0e249b2fadb5627b7018a05e819240603927200aacd268006eb28bff1d83352543e7c37ef6fdabe80ebd266f45935d82e0ae", "commentary": "", "date": "2024-11-02T12:30:49", "faintNoteMode": 0, "handled": 8, "hitPointsMode": 5, "inputFavorMode": 0, "inputFlags": 1, "isBand1": true, "isF": false, "isPaused": false, "judgmentMode": 1, "longNoteMode": 0, "lowestJudgmentConditionMode": 0, "multiplier": 10.509872832369943, "noteMobilityMode": 0, "noteModifyMode": 0, "noteSaltMode": 0, "point": 1.0, "salt": 14995140, "stand": 996211}, {"audioMultiplier": 1.0, "autoMode": 0, "avatarID": "zistered", "avatarName": " Zistered", "band": 1003, "commentID": "348cc2a8e778732c06e9c7954c4a3789ae3ee5b0c6c2508c825075f79fe7618b8e879f390e8f730900ed0983ff321759ca94d0e6e0ba580d412a344d9f6f94a1", "commentary": "", "date": "2025-02-06T04:00:02", "faintNoteMode": 0, "handled": 8, "hitPointsMode": 8, "inputFavorMode": 0, "inputFlags": 1, "isBand1": true, "isF": false, "isPaused": false, "judgmentMode": 1, "longNoteMode": 0, "lowestJudgmentConditionMode": 0, "multiplier": 8.38150289017341, "noteMobilityMode": 0, "noteModifyMode": 0, "noteSaltMode": 0, "point": 1.0, "salt": 8797296, "stand": 995513}, {"audioMultiplier": 1.0, "autoMode": 0, "avatarID": "~76561198331850841", "avatarName": "경기도 성남시 분당구", "band": 1003, "commentID": "59e8ac02854b4dfa4bb481cc702403ae3a68229371c4454c78fa9d53530c9e3715199b03f3ab9d8def1a65ea95061c2242d993ff3165f2f8c2130acba4f68242", "commentary": "", "date": "2026-05-07T13:01:02", "faintNoteMode": 0, "handled": 8, "hitPointsMode": 5, "inputFavorMode": 0, "inputFlags": 1, "isBand1": true, "isF": false, "isPaused": false, "judgmentMode": 1, "longNoteMode": 0, "lowestJudgmentConditionMode": 0, "multiplier": 7.414670520231213, "noteMobilityMode": 0, "noteModifyMode": 0, "noteSaltMode": 0, "point": 1.0, "salt": 587655328, "stand": 995314}, {"audioMultiplier": 1.0, "autoMode": 0, "avatarID": "psb703", "avatarName": "plug", "band": 1003, "commentID": "b3f501c9f8f3fe7c7debdb71e5a16bd54b23113ae2542acd0630a4321beccd006b83eeb74194a3eb704f7a5173ccd77847910c1ddb6d7804655453ae8d0c75e9", "commentary": "", "date": "2026-01-15T10:14:14", "faintNoteMode": 0, "handled": 8, "hitPointsMode": 8, "inputFavorMode": 0, "inputFlags": 1, "isBand1": true, "isF": false, "isPaused": false, "judgmentMode": 1, "longNoteMode": 0, "lowestJudgmentConditionMode": 0, "multiplier": 7.428381502890173, "noteMobilityMode": 0, "noteModifyMode": 0, "noteSaltMode": 0, "point": 1.0, "salt": 17135625, "stand": 993818}, {"audioMultiplier": 1.0, "autoMode": 0, "avatarID": "kim2dosa", "avatarName": "[EFT]Shturman", "band": 999, "commentID": "ff60b0b6dc39311d3091b5d4d545295872d4ae3c7e0e42bb3323a1dc9c24b9a4da4aa79f3c566295292c91d80201948c6bcb969c9095d90bb9e20fc479fc81f5", "commentary": "", "date": "2025-10-03T16:48:32", "faintNoteMode": 0, "handled": 2, "hitPointsMode": 5, "inputFavorMode": 0, "inputFlags": 1, "isBand1": false, "isF": false, "isPaused": false, "judgmentMode": 1, "longNoteMode": 0, "lowestJudgmentConditionMode": 0, "multiplier": 11.213872832369942, "noteMobilityMode": 0, "noteModifyMode": 0, "noteSaltMode": 0, "point": 0.998703888334995, "salt": 16709328, "stand": 991226}, {"audioMultiplier": 1.0, "autoMode": 0, "avatarID": "dolsan23", "avatarName": "유리", "band": 1003, "commentID": "efc3674baddbb03dd6247ffb7b0a71fc1bbd0937a341f8ca58b5f95774eaf51219ad0cb48b81d3851c417d5bec9d72ca891ad05204a8ed69b423216d2e4a3f63", "commentary": "", "date": "2024-11-07T09:13:48", "faintNoteMode": 0, "handled": 2, "hitPointsMode": 5, "inputFavorMode": 0, "inputFlags": 1, "isBand1": true, "isF": false, "isPaused": false, "judgmentMode": 1, "longNoteMode": 0, "lowestJudgmentConditionMode": 0, "multiplier": 9.937919075144508, "noteMobilityMode": 0, "noteModifyMode": 0, "noteSaltMode": 0, "point": 0.9990029910269193, "salt": 26251500, "stand": 991126}, {"audioMultiplier": 1.0, "autoMode": 0, "avatarID": "oudopus", "avatarName": "젖소", "band": 1003, "commentID": "f8b1ac2c8abca40054ae3c1af56e37b4a0521c8d3b4673e75615b8be6474b7ffa9de4f1a1260f9a3acf73c1a117c4267f1a3e5588bf8658454cc238b95afbe21", "commentary": "", "date": "2023-12-13T08:51:56", "faintNoteMode": 0, "handled": 2, "hitPointsMode": 5, "inputFavorMode": 0, "inputFlags": 1, "isBand1": true, "isF": false, "isPaused": false, "judgmentMode": 1, "longNoteMode": 0, "lowestJudgmentConditionMode": 0, "multiplier": 8.319942196531784, "noteMobilityMode": 0, "noteModifyMode": 0, "noteSaltMode": 0, "point": 0.9997008973080758, "salt": 27735687, "stand": 989232}, {"audioMultiplier": 1.0, "autoMode": 0, "avatarID": "kim8263", "avatarName": "CoolRyong", "band": 1003, "commentID": "39e6f74adef09a6bdbc567b82edbbcf79076d4da8a5ce22573ebb4fd5dcc865d2df1042fa9774e0dc7c842f2ce1fbb90ccd75389fb114e806c365b9f51f2b145", "commentary": "", "date": "2024-12-06T12:12:41", "faintNoteMode": 0, "handled": 8, "hitPointsMode": 8, "inputFavorMode": 0, "inputFlags": 1, "isBand1": true, "isF": false, "isPaused": false, "judgmentMode": 1, "longNoteMode": 0, "lowestJudgmentConditionMode": 0, "multiplier": 6.6473988439306355, "noteMobilityMode": 0, "noteModifyMode": 0, "noteSaltMode": 0, "point": 1.0, "salt": 21674140, "stand": 989132}, {"audioMultiplier": 1.0, "autoMode": 0, "avatarID": "~76561199033698698", "avatarName": "ANAList", "band": 1003, "commentID": "fceb61de6e05b3187ae04d664322b62f7179fb0510b889af2c4dd64bb7439aeef3692cf3eb8b295d2246e2f588a450097f894c89a08ef4baf25aefac406812db", "commentary": "", "date": "2025-09-26T13:42:34", "faintNoteMode": 0, "handled": 8, "hitPointsMode": 8, "inputFavorMode": 0, "inputFlags": 1, "isBand1": true, "isF": false, "isPaused": false, "judgmentMode": 1, "longNoteMode": 0, "lowestJudgmentConditionMode": 0, "multiplier": 7.5994855491329485, "noteMobilityMode": 0, "noteModifyMode": 0, "noteSaltMode": 0, "point": 1.0, "salt": 38204843, "stand": 988035}, {"audioMultiplier": 1.0, "autoMode": 0, "avatarID": "jk0059", "avatarName": "MENEEE", "band": 1003, "commentID": "5f4601169b1fe3fabc610836156009f12bf6cf7925fdef3caea3ce9ef7017d5aa138c265e29a1d8f98552e1c0a0c178b50a9b6de836914d8e8d77439ac5efe00", "commentary": "", "date": "2024-09-22T08:03:52", "faintNoteMode": 0, "handled": 2, "hitPointsMode": 5, "inputFavorMode": 0, "inputFlags": 1, "isBand1": true, "isF": false, "isPaused": false, "judgmentMode": 1, "longNoteMode": 0, "lowestJudgmentConditionMode": 0, "multiplier": 9.452774566473988, "noteMobilityMode": 0, "noteModifyMode": 0, "noteSaltMode": 0, "point": 0.9997008973080758, "salt": 443914109, "stand": 988035}, {"audioMultiplier": 1.0, "autoMode": 0, "avatarID": "Playlist", "avatarName": "Playlist", "band": 1003, "commentID": "c0bbe554ef026685f85666f511f70d95df2c8c00453834cd4ed9ae8a8884b58af3c1b5e01ef046a346d9c1ce21bc4818af6167ca8aa231727650121f950a8e1a", "commentary": "", "date": "2026-07-11T11:59:10", "faintNoteMode": 0, "handled": 2, "hitPointsMode": 5, "inputFavorMode": 0, "inputFlags": 1, "isBand1": true, "isF": false, "isPaused": false, "judgmentMode": 1, "longNoteMode": 0, "lowestJudgmentConditionMode": 0, "multiplier": 8.092485549132949, "noteMobilityMode": 0, "noteModifyMode": 0, "noteSaltMode": 0, "point": 0.9994017946161515, "salt": 16577718, "stand": 987936}, {"audioMultiplier": 1.0, "autoMode": 0, "avatarID": "studydiein4", "avatarName": "타치바나 셰리", "band": 1003, "commentID": "e8a6438bfed10d7f36ec54f071a9079ba8f07774a62c0b4b46da9c55c55019eb4df12183a91033ebbe4c2fefd383b8142d072d4fecd51a7afd23f64ef6a0903e", "commentary": "", "date": "2026-04-11T17:28:08", "faintNoteMode": 0, "handled": 2, "hitPointsMode": 3, "inputFavorMode": 0, "inputFlags": 1, "isBand1": true, "isF": false, "isPaused": false, "judgmentMode": 1, "longNoteMode": 0, "lowestJudgmentConditionMode": 0, "multiplier": 9.560693641618498, "noteMobilityMode": 0, "noteModifyMode": 0, "noteSaltMode": 0, "point": 0.9980059820538387, "salt": 7606593, "stand": 987746}, {"audioMultiplier": 1.0, "autoMode": 0, "avatarID": "SolgrynTheGamer", "avatarName": "Solgryn", "band": 980, "commentID": "7a5fd49027cf6df6ffc810aa23a457e47957fed08d0bc98644a9efeb19d2be270e1197e6f17eef0c015210b287b828fb699e7f52652bf3fa66da8bdcbf99cd42", "commentary": "", "date": "2023-12-04T12:24:08", "faintNoteMode": 0, "handled": 6, "hitPointsMode": 5, "inputFavorMode": 0, "inputFlags": 1, "isBand1": false, "isF": false, "isPaused": false, "judgmentMode": 1, "longNoteMode": 0, "lowestJudgmentConditionMode": 0, "multiplier": 9.826589595375722, "noteMobilityMode": 0, "noteModifyMode": 0, "noteSaltMode": 0, "point": 0.9984047856430709, "salt": 44, "stand": 986739}, {"audioMultiplier": 1.0, "autoMode": 0, "avatarID": "issu328", "avatarName": "ISSU", "band": 1003, "commentID": "59ec86eb3c6a0a194547d7b649cfe097d3c3f574f515ee846c9d6beed5e6b24c7b4a727243019d18fe94b82630373e8f5ec7feff404e810d1468eec71bd12526", "commentary": "", "date": "2025-04-09T14:05:29", "faintNoteMode": 0, "handled": 2, "hitPointsMode": 3, "inputFavorMode": 0, "inputFlags": 1, "isBand1": true, "isF": false, "isPaused": false, "judgmentMode": 1, "longNoteMode": 0, "lowestJudgmentConditionMode": 0, "multiplier": 6.53757225433526, "noteMobilityMode": 0, "noteModifyMode": 0, "noteSaltMode": 0, "point": 0.9990029910269193, "salt": 540573281, "stand": 986640}, {"audioMultiplier": 1.0, "autoMode": 0, "avatarID": "lcpel1980", "avatarName": "Note", "band": 1003, "commentID": "b7851197334f0c642478088bc1788dc07ac299dc2cf4a2fca042dd672ced74c3f0ffeb048df04ff67bc563f1623e1df3ee0d184a027f166520bc83ed7a70e02e", "commentary": "", "date": "2025-03-12T14:03:25", "faintNoteMode": 0, "handled": 2, "hitPointsMode": 3, "inputFavorMode": 0, "inputFlags": 1, "isBand1": true, "isF": false, "isPaused": false, "judgmentMode": 1, "longNoteMode": 0, "lowestJudgmentConditionMode": 0, "multiplier": 9.820809248554914, "noteMobilityMode": 0, "noteModifyMode": 0, "noteSaltMode": 0, "point": 0.9994017946161516, "salt": 8051687, "stand": 986241}, {"audioMultiplier": 1.0, "autoMode": 0, "avatarID": "kjs330942", "avatarName": "Osara", "band": 1003, "commentID": "8c43862f810a1cdc500c6f7e0ae3cb79729c8fce858c22e3fe2ef056253f52aa2cf05330dac19f82ed496ece51bc5725164be5e889695e651b87a89b6236148e", "commentary": "", "date": "2025-06-08T14:21:47", "faintNoteMode": 0, "handled": 2, "hitPointsMode": 5, "inputFavorMode": 0, "inputFlags": 1, "isBand1": true, "isF": false, "isPaused": false, "judgmentMode": 1, "longNoteMode": 0, "lowestJudgmentConditionMode": 0, "multiplier": 8.352601156069364, "noteMobilityMode": 0, "noteModifyMode": 0, "noteSaltMode": 0, "point": 0.9991026919242273, "salt": 10625390, "stand": 986041}, {"audioMultiplier": 1.0, "autoMode": 0, "avatarID": "~76561199072097174", "avatarName": "ConstaX", "band": 1003, "commentID": "506451330c9d3390f563000d164c5e7489a37c0447a4aa59e2694f2f4b9e96bc4323bb2c0b5abd8adc0c2d3861691ee59befa12d5401ca808c8b8f4099398162", "commentary": "", "date": "2025-07-12T02:48:23", "faintNoteMode": 0, "handled": 2, "hitPointsMode": 1, "inputFavorMode": 0, "inputFlags": 1, "isBand1": true, "isF": false, "isPaused": false, "judgmentMode": 1, "longNoteMode": 0, "lowestJudgmentConditionMode": 0, "multiplier": 7.6473988439306355, "noteMobilityMode": 0, "noteModifyMode": 0, "noteSaltMode": 0, "point": 0.9983050847457626, "salt": 686421171, "stand": 985353}, {"audioMultiplier": 1.0, "autoMode": 0, "avatarID": "douny007", "avatarName": "KurRsive", "band": 1003, "commentID": "173ecdd11b0723844822c1a8f3af57f1ab848bd75d6bdab283bdee744ad0efe01083d0802fe9f7ba62a3a1bad7798569312f937ef9dd13bd31ffc26097f9a05c", "commentary": "", "date": "2024-10-19T05:43:28", "faintNoteMode": 0, "handled": 2, "hitPointsMode": 3, "inputFavorMode": 0, "inputFlags": 1, "isBand1": true, "isF": false, "isPaused": false, "judgmentMode": 1, "longNoteMode": 0, "lowestJudgmentConditionMode": 0, "multiplier": 6.358381502890174, "noteMobilityMode": 0, "noteModifyMode": 0, "noteSaltMode": 0, "point": 0.9982053838484547, "salt": 1126716328, "stand": 983659}, {"audioMultiplier": 1.0, "autoMode": 0, "avatarID": "haelangneul7596", "avatarName": "늘해랑", "band": 651, "commentID": "6e68c6ded295b4ae3ca43268537f2b61e1959b71e70485ad99a73117ee26ad33b19b58ea31f7908d449e703f6862c8b3b4bb1ea0438fdf89b604ded6a45af8fc", "commentary": "", "date": "2025-05-14T09:53:46", "faintNoteMode": 0, "handled": 6, "hitPointsMode": 5, "inputFavorMode": 0, "inputFlags": 1, "isBand1": false, "isF": false, "isPaused": false, "judgmentMode": 1, "longNoteMode": 0, "lowestJudgmentConditionMode": 0, "multiplier": 8.739884393063583, "noteMobilityMode": 0, "noteModifyMode": 0, "noteSaltMode": 0, "point": 0.9979062811565305, "salt": 25499906, "stand": 982462}, {"audioMultiplier": 1.0, "autoMode": 0, "avatarID": "kloky", "avatarName": "manul", "band": 1003, "commentID": "ed96f9f1be024573f3f672f65b117d990d5cbb8c77738f093824e43538f9395eb3e9d732d14a39a064b498c79db354a51889d05512d7e1d928d13d9fda03755f", "commentary": "", "date": "2025-01-16T09:42:40", "faintNoteMode": 0, "handled": 2, "hitPointsMode": 5, "inputFavorMode": 0, "inputFlags": 1, "isBand1": true, "isF": false, "isPaused": false, "judgmentMode": 1, "longNoteMode": 0, "lowestJudgmentConditionMode": 0, "multiplier": 6.48150289017341, "noteMobilityMode": 0, "noteModifyMode": 0, "noteSaltMode": 0, "point": 0.9985044865403788, "salt": 23500312, "stand": 982253}, {"audioMultiplier": 1.0, "autoMode": 0, "avatarID": "roadwara", "avatarName": "Tantn", "band": 399, "commentID": "f089a5dc3adf95d25794799240657687cfcdb8db73a4ac9f6a0716499b56242fcf540a0317bc275534e790ac59d2be446fa3a474c501bbd4b3ac44a4021520be", "commentary": "", "date": "2025-02-16T09:54:55", "faintNoteMode": 0, "handled": 6, "hitPointsMode": 5, "inputFavorMode": 0, "inputFlags": 1, "isBand1": false, "isF": false, "isPaused": false, "judgmentMode": 1, "longNoteMode": 0, "lowestJudgmentConditionMode": 0, "multiplier": 8.781387283236999, "noteMobilityMode": 0, "noteModifyMode": 0, "noteSaltMode": 0, "point": 0.9971086739780659, "salt": 20446656, "stand": 981754}, {"audioMultiplier": 1.0, "autoMode": 0, "avatarID": "~76561199608575383", "avatarName": "BSTC", "band": 1003, "commentID": "8e5ae49f6cff6ea65a0e0e3960b7feb959d4b7dfc92adc51d3bda297dd5449ff085b073890c7c1b6518c854aa5d1ad1afd68ef914da99877da1c684d67a9a958", "commentary": "", "date": "2025-10-03T10:33:04", "faintNoteMode": 0, "handled": 2, "hitPointsMode": 3, "inputFavorMode": 0, "inputFlags": 1, "isBand1": true, "isF": false, "isPaused": false, "judgmentMode": 1, "longNoteMode": 0, "lowestJudgmentConditionMode": 0, "multiplier": 7.341040462427745, "noteMobilityMode": 0, "noteModifyMode": 0, "noteSaltMode": 0, "point": 0.9994017946161516, "salt": 3186921, "stand": 981256}, {"audioMultiplier": 1.0, "autoMode": 0, "avatarID": "~76561198799664621", "avatarName": "SignalFE", "band": 515, "commentID": "cb15f69d42381c1ba3b27ec757be7a56490cf388f35cfcc02d4b982698dc5e79327dfe69396bf774a470ae44b471479668f7e4e5dc37817f70f7b200a216e93f", "commentary": "", "date": "2025-12-10T16:08:27", "faintNoteMode": 0, "handled": 6, "hitPointsMode": 5, "inputFavorMode": 0, "inputFlags": 1, "isBand1": false, "isF": false, "isPaused": false, "judgmentMode": 1, "longNoteMode": 0, "lowestJudgmentConditionMode": 0, "multiplier": 7.514450867052023, "noteMobilityMode": 0, "noteModifyMode": 0, "noteSaltMode": 0, "point": 0.9968095712861416, "salt": 258064015, "stand": 979062}, {"audioMultiplier": 1.0, "autoMode": 0, "avatarID": "develryan", "avatarName": "꼬소준아", "band": 1003, "commentID": "ba11327303e015f2b7ec223fcf94373c642474233847d1e20947229f683a0429b577ed631fe1af4dad44c3f850dab7401db729016bd4afd3d4d7abb4e864e4e4", "commentary": "", "date": "2024-03-06T18:05:13", "faintNoteMode": 0, "handled": 2, "hitPointsMode": 5, "inputFavorMode": 0, "inputFlags": 1, "isBand1": true, "isF": false, "isPaused": false, "judgmentMode": 1, "longNoteMode": 0, "lowestJudgmentConditionMode": 0, "multiplier": 7.797109826589596, "noteMobilityMode": 0, "noteModifyMode": 0, "noteSaltMode": 0, "point": 0.9980059820538385, "salt": 24478015, "stand": 978773}, {"audioMultiplier": 1.0, "autoMode": 0, "avatarID": "a4725458", "avatarName": "IDDDIID", "band": 700, "commentID": "2435675a166db7782e47cb31561be9793bf93e3cf90cc1115eed5d15a77fecc29ca122ba8879c78132222258fa1bd6cabaff87f33a54d9f7f5ff113f34f2a730", "commentary": "", "date": "2025-02-22T08:44:15", "faintNoteMode": 0, "handled": 1, "hitPointsMode": 1, "inputFavorMode": 0, "inputFlags": 1, "isBand1": false, "isF": false, "isPaused": false, "judgmentMode": 1, "longNoteMode": 0, "lowestJudgmentConditionMode": 0, "multiplier": 8.796531791907514, "noteMobilityMode": 0, "noteModifyMode": 0, "noteSaltMode": 0, "point": 0.9964107676969094, "salt": 53512515, "stand": 978584}, {"audioMultiplier": 1.0, "autoMode": 0, "avatarID": "~76561198061507413", "avatarName": "Rastar", "band": 578, "commentID": "bc5af721d49c09c14fb7dba3806d3160fa67fc34392985a99f8bddf8bc703c6cbe23f7317c2fa261d04778925054eccb34a081d8a69ca1df1c09eeb170a31680", "commentary": "", "date": "2025-08-06T07:52:54", "faintNoteMode": 0, "handled": 6, "hitPointsMode": 5, "inputFavorMode": 0, "inputFlags": 1, "isBand1": false, "isF": false, "isPaused": false, "judgmentMode": 1, "longNoteMode": 0, "lowestJudgmentConditionMode": 0, "multiplier": 8.092485549132949, "noteMobilityMode": 0, "noteModifyMode": 0, "noteSaltMode": 0, "point": 0.9978065802592224, "salt": 8043078, "stand": 976969}, {"audioMultiplier": 1.0, "autoMode": 0, "avatarID": "moron9564", "avatarName": "Nentsy", "band": 1003, "commentID": "43db01d2828d3899345bca7712d8b7cb65b937768fc0eff2ca04d3b1209b6de3c783b199a4c57c23e7dde0b8e9eb427e79043816d6bd36e7135b0361688dfbd1", "commentary": "", "date": "2024-03-16T01:51:02", "faintNoteMode": 0, "handled": 2, "hitPointsMode": 5, "inputFavorMode": 0, "inputFlags": 1, "isBand1": true, "isF": false, "isPaused": false, "judgmentMode": 1, "longNoteMode": 0, "lowestJudgmentConditionMode": 0, "multiplier": 8.485549132947977, "noteMobilityMode": 0, "noteModifyMode": 0, "noteSaltMode": 0, "point": 0.9971086739780658, "salt": 53474984, "stand": 975692}, {"audioMultiplier": 1.0, "autoMode": 0, "avatarID": "ab8868qwe", "avatarName": "[EFT]Sanitar", "band": 1003, "commentID": "1707a743a9aced8c208f485a0f306472b1df144b4c012d6ed7935d2b89b9a8079988f8cf8d844d2165423d9a678f9f8330cfdc64f033582a7355d45e4c5a41fb", "commentary": "", "date": "2024-12-05T14:43:52", "faintNoteMode": 0, "handled": 2, "hitPointsMode": 3, "inputFavorMode": 0, "inputFlags": 1, "isBand1": true, "isF": false, "isPaused": false, "judgmentMode": 1, "longNoteMode": 0, "lowestJudgmentConditionMode": 0, "multiplier": 11.560693641618498, "noteMobilityMode": 0, "noteModifyMode": 0, "noteSaltMode": 0, "point": 0.995912263210369, "salt": 434244406, "stand": 975383}, {"audioMultiplier": 1.0, "autoMode": 0, "avatarID": "gloryday9760", "avatarName": "桜羽_エマ†", "band": 542, "commentID": "2a36d7a25f45e92a3f0db54e56db76fae47711380a9998a4f05e15dc72acbf1f6e35be3ea7ab1195a58a4b7f4de7bb0fb22c50f12ed8e7bae3395890402f5489", "commentary": "", "date": "2025-09-25T15:26:55", "faintNoteMode": 0, "handled": 6, "hitPointsMode": 5, "inputFavorMode": 0, "inputFlags": 1, "isBand1": false, "isF": false, "isPaused": false, "judgmentMode": 1, "longNoteMode": 0, "lowestJudgmentConditionMode": 0, "multiplier": 9.76878612716763, "noteMobilityMode": 0, "noteModifyMode": 0, "noteSaltMode": 0, "point": 0.9939182452642077, "salt": 8460640, "stand": 974995}, {"audioMultiplier": 1.0, "autoMode": 0, "avatarID": "~76561198099934244", "avatarName": "ZoiM", "band": 1003, "commentID": "2659ec95fec0831227f26db5776371d2d96b33865dbbb35b1e7637ef520684e16fcdec813a303177837d27b7f50bc8483bf9d024ca3f82607dac67dd3ee613fe", "commentary": "", "date": "2025-05-25T03:18:43", "faintNoteMode": 0, "handled": 2, "hitPointsMode": 3, "inputFavorMode": 0, "inputFlags": 1, "isBand1": true, "isF": false, "isPaused": false, "judgmentMode": 1, "longNoteMode": 0, "lowestJudgmentConditionMode": 0, "multiplier": 7.343121387283237, "noteMobilityMode": 0, "noteModifyMode": 0, "noteSaltMode": 0, "point": 0.9976071784646062, "salt": 322697703, "stand": 974905}, {"audioMultiplier": 1.0, "autoMode": 0, "avatarID": "~76561198412161998", "avatarName": "미로게임", "band": 859, "commentID": "8bd889a72f1c6b31a69e00bce7c588581fa1a89ac8d1c604e797914eba3c02e5e07733800ba1d4a12419148addfdae1957d83192f682782120c31b150f67051f", "commentary": "", "date": "2026-02-11T16:17:19", "faintNoteMode": 0, "handled": 6, "hitPointsMode": 5, "inputFavorMode": 0, "inputFlags": 1, "isBand1": false, "isF": false, "isPaused": false, "judgmentMode": 1, "longNoteMode": 0, "lowestJudgmentConditionMode": 0, "multiplier": 9.617456647398843, "noteMobilityMode": 0, "noteModifyMode": 0, "noteSaltMode": 0, "point": 0.9956131605184448, "salt": 1737161156, "stand": 974077}, {"audioMultiplier": 1.0, "autoMode": 0, "avatarID": "cccc3999", "avatarName": "휴맨시티", "band": 712, "commentID": "b0a9d12308b9e99a09bb734f687eceeb4a3a11bda9cf1a6cec29fc72e9721b2612238a1707cdcd8110acfe46fb384c7349ea19d424c14fd5b783bb91c80580fd", "commentary": "", "date": "2025-01-24T08:00:10", "faintNoteMode": 0, "handled": 6, "hitPointsMode": 5, "inputFavorMode": 0, "inputFlags": 1, "isBand1": false, "isF": false, "isPaused": false, "judgmentMode": 1, "longNoteMode": 0, "lowestJudgmentConditionMode": 0, "multiplier": 8.38150289017341, "noteMobilityMode": 0, "noteModifyMode": 0, "noteSaltMode": 0, "point": 0.994516450648056, "salt": 47071921, "stand": 973998}, {"audioMultiplier": 1.0, "autoMode": 0, "avatarID": "~76561198046626614", "avatarName": "겹계단보면기절하는사람", "band": 775, "commentID": "f0e56130742dc71284193b07f81df744e0d39510db5274772657fe1d9c246a42aee0f9bf49a4ac2eb98c3f8fa2c4e9493b0644911d110e72e05623582728dfa4", "commentary": "", "date": "2025-05-18T04:31:25", "faintNoteMode": 0, "handled": 6, "hitPointsMode": 5, "inputFavorMode": 0, "inputFlags": 1, "isBand1": false, "isF": false, "isPaused": false, "judgmentMode": 1, "longNoteMode": 0, "lowestJudgmentConditionMode": 0, "multiplier": 8.670520231213873, "noteMobilityMode": 0, "noteModifyMode": 0, "noteSaltMode": 0, "point": 0.9954137587238286, "salt": 99810953, "stand": 973310}, {"audioMultiplier": 1.0, "autoMode": 0, "avatarID": "~76561198796738830", "avatarName": "Egosa", "band": 459, "commentID": "5e9be1bc8d2d42915ae10570c062ca2e18109e0e568792814777fcc41b5269e1cd3cdf0424d500dc076792fdbfa7f3bda5cc93f1240d059f05efbe5ca1653755", "commentary": "", "date": "2025-12-16T00:01:03", "faintNoteMode": 0, "handled": 6, "hitPointsMode": 5, "inputFavorMode": 0, "inputFlags": 1, "isBand1": false, "isF": false, "isPaused": false, "judgmentMode": 1, "longNoteMode": 0, "lowestJudgmentConditionMode": 0, "multiplier": 9.352601156069364, "noteMobilityMode": 0, "noteModifyMode": 0, "noteSaltMode": 0, "point": 0.9950149551345965, "salt": 2327687, "stand": 973080}, {"audioMultiplier": 1.0, "autoMode": 0, "avatarID": "~76561198249166020", "avatarName": "SXXK", "band": 1003, "commentID": "e0b9bafc12f6936c882d30b834a664f004b186637f3e61396994bd3ed847a277d894d4677b96ed40257de7c7e5d2b0ed4a97f927f64d35e60bb23db8d6e70a1f", "commentary": "", "date": "2025-12-10T08:29:27", "faintNoteMode": 0, "handled": 2, "hitPointsMode": 3, "inputFavorMode": 0, "inputFlags": 1, "isBand1": true, "isF": false, "isPaused": false, "judgmentMode": 1, "longNoteMode": 0, "lowestJudgmentConditionMode": 0, "multiplier": 8.335260115606937, "noteMobilityMode": 0, "noteModifyMode": 0, "noteSaltMode": 0, "point": 0.9954137587238289, "salt": 237894421, "stand": 971006}, {"audioMultiplier": 1.0, "autoMode": 0, "avatarID": "~76561199044476993", "avatarName": "가야오빠세컨드여친セ", "band": 997, "commentID": "3e81a1d4936dbe251287606c4624265411b49e140da5560bf48bf2468e7e16e07d4a7d972cb4e6525714cb20a607923b00eece1f82c9bdb8611fa6999fc4443b", "commentary": "", "date": "2026-05-18T09:04:01", "faintNoteMode": 0, "handled": 6, "hitPointsMode": 5, "inputFavorMode": 0, "inputFlags": 1, "isBand1": false, "isF": false, "isPaused": false, "judgmentMode": 1, "longNoteMode": 0, "lowestJudgmentConditionMode": 0, "multiplier": 8.109826589595375, "noteMobilityMode": 0, "noteModifyMode": 0, "noteSaltMode": 0, "point": 0.9960119641076772, "salt": 7889484, "stand": 968693}, {"audioMultiplier": 1.0, "autoMode": 0, "avatarID": "primorye", "avatarName": "Pmo", "band": 1003, "commentID": "4d1b9a656e81524b25f6cb4babede89369a19f7259d307c55808922b0711f03b6aa7c81e3583ebeca0ee8009793ae6443a6500090d77ebf6c9c160a0818a985b", "commentary": "", "date": "2024-01-12T02:42:44", "faintNoteMode": 0, "handled": 2, "hitPointsMode": 5, "inputFavorMode": 0, "inputFlags": 1, "isBand1": true, "isF": false, "isPaused": false, "judgmentMode": 1, "longNoteMode": 0, "lowestJudgmentConditionMode": 0, "multiplier": 6.0957225433526006, "noteMobilityMode": 0, "noteModifyMode": 0, "noteSaltMode": 4, "point": 0.9961116650049852, "salt": 72144281, "stand": 967726}, {"audioMultiplier": 1.0, "autoMode": 0, "avatarID": "~76561199018205344", "avatarName": "검은멸치", "band": 542, "commentID": "57dd5a407281f6d53438947e9826bf8a3ab6685ce5272a23587c988d92cffc44f78f1b84b7aeecdf968b45fb24414d6a0f4f4cfc39f5bf19078ea4b19ca297da", "commentary": "", "date": "2025-11-20T02:22:21", "faintNoteMode": 0, "handled": 6, "hitPointsMode": 5, "inputFavorMode": 0, "inputFlags": 1, "isBand1": false, "isF": false, "isPaused": false, "judgmentMode": 1, "longNoteMode": 0, "lowestJudgmentConditionMode": 0, "multiplier": 7.667225433526012, "noteMobilityMode": 0, "noteModifyMode": 0, "noteSaltMode": 0, "point": 0.9960119641076772, "salt": 91903937, "stand": 967597}, {"audioMultiplier": 1.0, "autoMode": 0, "avatarID": "kdh99889", "avatarName": "해껄룩", "band": 1003, "commentID": "c750d5d9ac34df196e5af5d71183c6ad86692cea4dd154d89aa41d3f563afbdb264b377172e39fce3578c35d0f7e51dae84280ddaa313bf2f9dfa87482bf56f3", "commentary": "", "date": "2025-01-24T19:22:47", "faintNoteMode": 0, "handled": 2, "hitPointsMode": 3, "inputFavorMode": 0, "inputFlags": 1, "isBand1": true, "isF": false, "isPaused": false, "judgmentMode": 1, "longNoteMode": 0, "lowestJudgmentConditionMode": 0, "multiplier": 9.248554913294798, "noteMobilityMode": 0, "noteModifyMode": 0, "noteSaltMode": 0, "point": 0.9954137587238286, "salt": 856115859, "stand": 966819}, {"audioMultiplier": 1.0, "autoMode": 1, "avatarID": "~76561199058321844", "avatarName": "둘리", "band": 489, "commentID": "50c69fcfe417e0c1c110bbf72436504d07367a0cefbda6f269d010c9e978f406ab2d066b681ce3c18b29558dd0ffe81aaedb9fac751ffd37e8adf5a80b2fb73a", "commentary": "", "date": "2026-01-24T00:54:28", "faintNoteMode": 0, "handled": 6, "hitPointsMode": 5, "inputFavorMode": 0, "inputFlags": 1, "isBand1": false, "isF": false, "isPaused": false, "judgmentMode": 1, "longNoteMode": 0, "lowestJudgmentConditionMode": 0, "multiplier": 8.245086705202313, "noteMobilityMode": 0, "noteModifyMode": 0, "noteSaltMode": 0, "point": 0.9929212362911267, "salt": 13776546, "stand": 966340}, {"audioMultiplier": 1.0, "autoMode": 0, "avatarID": "chyanbagi", "avatarName": "바기", "band": 872, "commentID": "3bd699f95377a4e50a08a06bf3632add94a3353bcf3df2205d051de6e199640a7438399776d50ed0b1db42be7564b415c5219f1eab07ff720e6c18d6ab2be37d", "commentary": "", "date": "2025-04-03T08:16:33", "faintNoteMode": 0, "handled": 6, "hitPointsMode": 5, "inputFavorMode": 0, "inputFlags": 1, "isBand1": false, "isF": false, "isPaused": false, "judgmentMode": 1, "longNoteMode": 0, "lowestJudgmentConditionMode": 0, "multiplier": 8.38150289017341, "noteMobilityMode": 0, "noteModifyMode": 0, "noteSaltMode": 0, "point": 0.9950149551345964, "salt": 90052265, "stand": 966321}, {"audioMultiplier": 1.0, "autoMode": 0, "avatarID": "kgy9948", "avatarName": "유우카", "band": 720, "commentID": "6526d0c900f2630e1218c7daa79df06e29c1cac446de8282cfba7649fee7046828278bc8a9b941ce135efbbef972f2fd9d1592ee9b55c2245ed003f4eb239027", "commentary": "It's hard.", "date": "2024-08-14T12:22:19", "faintNoteMode": 0, "handled": 6, "hitPointsMode": 5, "inputFavorMode": 0, "inputFlags": 1, "isBand1": false, "isF": false, "isPaused": false, "judgmentMode": 1, "longNoteMode": 0, "lowestJudgmentConditionMode": 0, "multiplier": 11.38728323699422, "noteMobilityMode": 0, "noteModifyMode": 0, "noteSaltMode": 0, "point": 0.993220338983051, "salt": 10451703, "stand": 966241}, {"audioMultiplier": 1.0, "autoMode": 0, "avatarID": "umsuhwan56", "avatarName": "Hwan", "band": 1003, "commentID": "039015343c1fd65d4ef73fe0299aabc467f4017edb7c93800ed3471307fdcc1d994a6ea77923c23e51e7302c2f2a34291678eb1025cc37d22f3d48205ca360e4", "commentary": "", "date": "2025-02-22T10:36:04", "faintNoteMode": 0, "handled": 2, "hitPointsMode": 1, "inputFavorMode": 0, "inputFlags": 1, "isBand1": true, "isF": false, "isPaused": false, "judgmentMode": 1, "longNoteMode": 0, "lowestJudgmentConditionMode": 0, "multiplier": 11.38728323699422, "noteMobilityMode": 0, "noteModifyMode": 0, "noteSaltMode": 0, "point": 0.994416749750748, "salt": 692242500, "stand": 965942}, {"audioMultiplier": 1.0, "autoMode": 0, "avatarID": "adeyhungjoke", "avatarName": "Ouy", "band": 369, "commentID": "dd7fc9badf7228e3bde049b0b713ef3602bd45e133231f3f435770934c0627bfd4e996614ea9dd039dea9b974677eb5885f9d49e810315f4977d534d296c9067", "commentary": "", "date": "2026-01-19T06:12:30", "faintNoteMode": 0, "handled": 6, "hitPointsMode": 5, "inputFavorMode": 0, "inputFlags": 1, "isBand1": false, "isF": false, "isPaused": false, "judgmentMode": 1, "longNoteMode": 0, "lowestJudgmentConditionMode": 0, "multiplier": 8.196531791907514, "noteMobilityMode": 0, "noteModifyMode": 0, "noteSaltMode": 0, "point": 0.9923230309072784, "salt": 705453, "stand": 965314}, {"audioMultiplier": 1.0, "autoMode": 0, "avatarID": "~76561198101984489", "avatarName": "보이면3초컷", "band": 862, "commentID": "d5b133d60ceb6741eece46b8dbcce27e8b03c17a44db37a2a10159e130191a363b9d94c104e4ac38f09ecfa467f8e0e700cd4f7c2e6fad2db5abc5f3944e43d3", "commentary": "", "date": "2025-09-07T13:45:52", "faintNoteMode": 0, "handled": 6, "hitPointsMode": 5, "inputFavorMode": 0, "inputFlags": 1, "isBand1": false, "isF": false, "isPaused": false, "judgmentMode": 1, "longNoteMode": 0, "lowestJudgmentConditionMode": 0, "multiplier": 7.500982658959538, "noteMobilityMode": 0, "noteModifyMode": 0, "noteSaltMode": 0, "point": 0.992921236291127, "salt": 686154671, "stand": 964935}, {"audioMultiplier": 1.0, "autoMode": 0, "avatarID": "daze3450", "avatarName": "데이즈", "band": 1003, "commentID": "09c9671b9ff1e46df0d702368451ad8d135d7f1611d870abb62358ee3c1fc6b52847a5f22da72cfdfe852c5e7b2bfb0a4c59b54f36d4840389c7dd4461d19cf9", "commentary": "", "date": "2024-06-15T10:26:13", "faintNoteMode": 0, "handled": 2, "hitPointsMode": 3, "inputFavorMode": 0, "inputFlags": 1, "isBand1": true, "isF": false, "isPaused": false, "judgmentMode": 1, "longNoteMode": 0, "lowestJudgmentConditionMode": 0, "multiplier": 6.971098265895954, "noteMobilityMode": 0, "noteModifyMode": 0, "noteSaltMode": 0, "point": 0.9970089730807576, "salt": 24656625, "stand": 964606}, {"audioMultiplier": 1.0, "autoMode": 0, "avatarID": "~76561198413562277", "avatarName": "잉여치", "band": 779, "commentID": "186258308362f0e146d8f49f63030c77d000c29827be441d6b4aa0f9e886d6baf14f592109068f569e96f1a1b99273f6d8c7eb91cd70039aa721bbe41090e97e", "commentary": "", "date": "2025-12-08T13:13:41", "faintNoteMode": 0, "handled": 6, "hitPointsMode": 5, "inputFavorMode": 0, "inputFlags": 1, "isBand1": false, "isF": false, "isPaused": false, "judgmentMode": 1, "longNoteMode": 0, "lowestJudgmentConditionMode": 0, "multiplier": 6.358381502890174, "noteMobilityMode": 0, "noteModifyMode": 0, "noteSaltMode": 0, "point": 0.9940179461615157, "salt": 862945625, "stand": 964346}, {"audioMultiplier": 1.0, "autoMode": 0, "avatarID": "canopus_avon", "avatarName": "Cano/*us", "band": 721, "commentID": "f371f4a419d3937c68c3e66652574ff19a48ad301bc9ce170018c435b6708406426ee756e44d4e0b96867e7a546e5db39b34f4e1ca3c46f81e0a70b39b74f109", "commentary": "", "date": "2023-12-08T10:32:39", "faintNoteMode": 0, "handled": 6, "hitPointsMode": 5, "inputFavorMode": 0, "inputFlags": 1, "isBand1": false, "isF": false, "isPaused": false, "judgmentMode": 1, "longNoteMode": 0, "lowestJudgmentConditionMode": 0, "multiplier": 7.531791907514451, "noteMobilityMode": 0, "noteModifyMode": 0, "noteSaltMode": 0, "point": 0.9933200398803591, "salt": 165493609, "stand": 962851}, {"audioMultiplier": 1.0, "autoMode": 0, "avatarID": "32comma", "avatarName": "32comma", "band": 1003, "commentID": "60e85586e4cabb3e83c65d209b068da221f6884aeb63f3fbbe72f757ed430b87ba8b8d71dc6e97c3f777e1baa4082334f611151fbc037f659cb2f0071b62d033", "commentary": "", "date": "2024-03-16T08:59:24", "faintNoteMode": 0, "handled": 2, "hitPointsMode": 5, "inputFavorMode": 0, "inputFlags": 1, "isBand1": true, "isF": false, "isPaused": false, "judgmentMode": 1, "longNoteMode": 0, "lowestJudgmentConditionMode": 0, "multiplier": 7.578034682080925, "noteMobilityMode": 0, "noteModifyMode": 0, "noteSaltMode": 0, "point": 0.9955134596211366, "salt": 10175703, "stand": 962013}, {"audioMultiplier": 1.0, "autoMode": 0, "avatarID": "rlaqkrchl", "avatarName": "스쿠로미", "band": 1003, "commentID": "b7481ba543c70e1be92f4af04a160610afe84153d41dc52d2a43f17f4d6c52efa52a8b47cd2b9e9ae0dd26decf021340fcace00e0c960b19696621b23986b9f0", "commentary": "", "date": "2025-02-17T10:13:22", "faintNoteMode": 0, "handled": 2, "hitPointsMode": 3, "inputFavorMode": 0, "inputFlags": 1, "isBand1": true, "isF": false, "isPaused": false, "judgmentMode": 1, "longNoteMode": 0, "lowestJudgmentConditionMode": 0, "multiplier": 7.535838150289018, "noteMobilityMode": 0, "noteModifyMode": 0, "noteSaltMode": 0, "point": 0.997308075772682, "salt": 32919500, "stand": 961615}, {"audioMultiplier": 1.0, "autoMode": 0, "avatarID": "arkinday", "avatarName": "arkinday", "band": 1003, "commentID": "bd164098ecb893cc3a738a82f416f7ad9be5cf56bc4f6e9fd59b55e0c3d17cf1e169784016a724b4ac13a2a41c2daf8358ed3d53f2c0fa21ec1ac8b0404b509d", "commentary": "", "date": "2026-01-25T10:35:16", "faintNoteMode": 0, "handled": 2, "hitPointsMode": 5, "inputFavorMode": 0, "inputFlags": 1, "isBand1": true, "isF": false, "isPaused": false, "judgmentMode": 2, "longNoteMode": 0, "lowestJudgmentConditionMode": 0, "multiplier": 9.826589595375722, "noteMobilityMode": 0, "noteModifyMode": 0, "noteSaltMode": 0, "point": 0.9938185443668995, "salt": 171481531, "stand": 959631}, {"audioMultiplier": 1.0, "autoMode": 0, "avatarID": "xeno7", "avatarName": "Xeno", "band": 711, "commentID": "51ad38ed00969701341945207361ad18f3cb826a782b84f43479fc6169170086b753ebc2e7b53852e2977f3510d616202b0e80d5631ad025144dc0213ace5bbb", "commentary": "", "date": "2025-03-23T06:46:58", "faintNoteMode": 0, "handled": 2, "hitPointsMode": 5, "inputFavorMode": 0, "inputFlags": 1, "isBand1": false, "isF": false, "isPaused": false, "judgmentMode": 1, "longNoteMode": 0, "lowestJudgmentConditionMode": 0, "multiplier": 6.647167630057804, "noteMobilityMode": 0, "noteModifyMode": 0, "noteSaltMode": 0, "point": 0.9938185443668995, "salt": 196231125, "stand": 958933}, {"audioMultiplier": 1.0, "autoMode": 0, "avatarID": "~76561198003705642", "avatarName": "옹견", "band": 1003, "commentID": "7a12077cdb9f12d2f12aaed039afa952421ee7d9b617839a9960b6d71d2b1da14b1572f2b5fd67c8bf39e9f6e60158954acc66ff46f57a504f29e04ff7b37818", "commentary": "", "date": "2025-09-08T10:54:03", "faintNoteMode": 0, "handled": 2, "hitPointsMode": 3, "inputFavorMode": 0, "inputFlags": 1, "isBand1": true, "isF": false, "isPaused": false, "judgmentMode": 1, "longNoteMode": 0, "lowestJudgmentConditionMode": 0, "multiplier": 8.057803468208093, "noteMobilityMode": 0, "noteModifyMode": 0, "noteSaltMode": 0, "point": 0.9953140578265207, "salt": 4067765, "stand": 958733}, {"audioMultiplier": 1.0, "autoMode": 0, "avatarID": "~76561198119858358", "avatarName": "hoihoi6914", "band": 565, "commentID": "c09c85002e0b9cace87be73780652e364d06cf242174d88e336b8b43ff37f9c950e8817e58dc97aa2a3c1cc5bc73e3b12c8d9065ea22ad5146f839e0d0d4fff6", "commentary": "", "date": "2026-03-22T05:49:38", "faintNoteMode": 0, "handled": 6, "hitPointsMode": 5, "inputFavorMode": 0, "inputFlags": 1, "isBand1": false, "isF": false, "isPaused": false, "judgmentMode": 1, "longNoteMode": 0, "lowestJudgmentConditionMode": 0, "multiplier": 7.402312138728323, "noteMobilityMode": 0, "noteModifyMode": 0, "noteSaltMode": 0, "point": 0.9920239282153543, "salt": 894532703, "stand": 953569}, {"audioMultiplier": 1.0, "autoMode": 0, "avatarID": "~76561198044749818", "avatarName": "Buster", "band": 864, "commentID": "51ce86f96d6accd985c8e3ffbd0ce6f790b2100428dc7c1553972cfc97eccfae05726676055549f858aadfe10ccd872e8130d42b9050e042342b860c0dcc63bc", "commentary": "", "date": "2025-05-21T16:53:06", "faintNoteMode": 0, "handled": 6, "hitPointsMode": 5, "inputFavorMode": 0, "inputFlags": 1, "isBand1": false, "isF": false, "isPaused": false, "judgmentMode": 1, "longNoteMode": 0, "lowestJudgmentConditionMode": 0, "multiplier": 7.502890173410405, "noteMobilityMode": 0, "noteModifyMode": 0, "noteSaltMode": 0, "point": 0.9898305084745764, "salt": 16179437, "stand": 952871}, {"audioMultiplier": 1.0, "autoMode": 0, "avatarID": "~76561198125814465", "avatarName": "Sayan-sama", "band": 495, "commentID": "e0a1f5cbff8c5377b218c1bad34001784f9b8535384a4da40dad2ed7eb01f786c64f455dd5f84474f5dc5190dfb859ae7b404830d696f3a33abee474e97e2fd6", "commentary": "", "date": "2025-09-22T14:59:41", "faintNoteMode": 0, "handled": 6, "hitPointsMode": 5, "inputFavorMode": 0, "inputFlags": 1, "isBand1": false, "isF": false, "isPaused": false, "judgmentMode": 1, "longNoteMode": 0, "lowestJudgmentConditionMode": 0, "multiplier": 10.757225433526012, "noteMobilityMode": 0, "noteModifyMode": 0, "noteSaltMode": 0, "point": 0.9884346959122634, "salt": 28141578, "stand": 951704}, {"audioMultiplier": 1.0, "autoMode": 0, "avatarID": "appleflavor", "avatarName": "appleflavor", "band": 465, "commentID": "03166bb8e0c64ffb521a3c1d1bd767d653516d7b0bb661fc27027bf573089e745e68319d3837421c2230c9a083cf35ae9a69c18316e7c3a92c18b550157dfd8c", "commentary": "", "date": "2025-11-07T15:10:31", "faintNoteMode": 0, "handled": 6, "hitPointsMode": 1, "inputFavorMode": 0, "inputFlags": 1, "isBand1": false, "isF": false, "isPaused": false, "judgmentMode": 1, "longNoteMode": 0, "lowestJudgmentConditionMode": 0, "multiplier": 8.601156069364162, "noteMobilityMode": 0, "noteModifyMode": 0, "noteSaltMode": 0, "point": 0.9869391824526422, "salt": 1497674171, "stand": 951704}, {"audioMultiplier": 1.0, "autoMode": 0, "avatarID": "~76561198006536328", "avatarName": "Heon", "band": 541, "commentID": "a89227e10899f86a1424feb6ef657d024dcabaad784c886cf14d0b9704370ccf927f96bf2991901d090c66fcc98b06fb06c1d6ce8b32e6e9a4a4cf911be11513", "commentary": "", "date": "2026-02-17T17:51:50", "faintNoteMode": 0, "handled": 6, "hitPointsMode": 5, "inputFavorMode": 0, "inputFlags": 1, "isBand1": false, "isF": false, "isPaused": false, "judgmentMode": 1, "longNoteMode": 0, "lowestJudgmentConditionMode": 0, "multiplier": 7.413294797687861, "noteMobilityMode": 0, "noteModifyMode": 0, "noteSaltMode": 0, "point": 0.9913260219341979, "salt": 383657671, "stand": 951585}, {"audioMultiplier": 1.0, "autoMode": 0, "avatarID": "moky85", "avatarName": "민초에용", "band": 441, "commentID": "334f7e3c3fbf891dd8959b838d45197f964673d61063e8c3dc3fb807e1ab058f4a80d136444d50d0c11d82851210fa3fc755f81958a6f7edc96bbf68aafa2c10", "commentary": "", "date": "2025-05-25T12:00:23", "faintNoteMode": 0, "handled": 6, "hitPointsMode": 5, "inputFavorMode": 0, "inputFlags": 1, "isBand1": false, "isF": false, "isPaused": false, "judgmentMode": 1, "longNoteMode": 0, "lowestJudgmentConditionMode": 0, "multiplier": 8.38150289017341, "noteMobilityMode": 0, "noteModifyMode": 0, "noteSaltMode": 0, "point": 0.9886227544910186, "salt": 464718, "stand": 951166}, {"audioMultiplier": 1.0, "autoMode": 0, "avatarID": "~76561199310038901", "avatarName": "ienaiakainoroi", "band": 1003, "commentID": "af1da0ec45d172000505cbdfc2b0b0e80f861e3fa8167716a46bbcabd15c5023a4dcf52f76ad537028dee4f3eca48b8993c2904c5fae5a27a1c2314e1112069a", "commentary": "", "date": "2025-08-26T11:31:23", "faintNoteMode": 0, "handled": 2, "hitPointsMode": 3, "inputFavorMode": 0, "inputFlags": 1, "isBand1": true, "isF": false, "isPaused": false, "judgmentMode": 1, "longNoteMode": 0, "lowestJudgmentConditionMode": 0, "multiplier": 6.618497109826589, "noteMobilityMode": 0, "noteModifyMode": 0, "noteSaltMode": 0, "point": 0.9923230309072787, "salt": 250247453, "stand": 951056}, {"audioMultiplier": 1.0, "autoMode": 0, "avatarID": "Moraku", "avatarName": "Moraku", "band": 386, "commentID": "be2bcb89e9d5b5d2aae40786a042370b55279f6111f65529d6c637be3f599fb358e6af7cbfcb3a4c47f9e8966f1655ca9c0cc487e1a4a3d2d2cc9fb1ad1ef49a", "commentary": "", "date": "2026-03-10T06:35:06", "faintNoteMode": 0, "handled": 6, "hitPointsMode": 5, "inputFavorMode": 0, "inputFlags": 1, "isBand1": false, "isF": false, "isPaused": false, "judgmentMode": 1, "longNoteMode": 0, "lowestJudgmentConditionMode": 0, "multiplier": 8.670520231213873, "noteMobilityMode": 0, "noteModifyMode": 0, "noteSaltMode": 0, "point": 0.9861415752741778, "salt": 10313968, "stand": 950309}, {"audioMultiplier": 1.0, "autoMode": 0, "avatarID": "~76561198411851755", "avatarName": "람다", "band": 601, "commentID": "a4283191114fc35a92122893942e77bf055fd4407692efb69cc9cb01a3de8cddc1975e2d50b163677b974f5fd46815f2ef1feacf1c39a84af83616534aba7711", "commentary": "", "date": "2025-10-01T10:51:42", "faintNoteMode": 0, "handled": 6, "hitPointsMode": 5, "inputFavorMode": 0, "inputFlags": 1, "isBand1": false, "isF": false, "isPaused": false, "judgmentMode": 1, "longNoteMode": 0, "lowestJudgmentConditionMode": 0, "multiplier": 7.964739884393064, "noteMobilityMode": 0, "noteModifyMode": 0, "noteSaltMode": 0, "point": 0.9910269192422736, "salt": 10411062, "stand": 949870}, {"audioMultiplier": 1.01, "autoMode": 0, "avatarID": "~76561198853010525", "avatarName": "통이아부지", "band": 385, "commentID": "dc8ce967abe049f7031dd5e41cd5c6b1a11271c5309303a49f486e522753368801cbf5ccea73a5bf036074e4ff3337c4c18519ff4a7bfa5ed267d259303275f7", "commentary": "", "date": "2025-10-15T17:49:30", "faintNoteMode": 0, "handled": 6, "hitPointsMode": 5, "inputFavorMode": 0, "inputFlags": 1, "isBand1": false, "isF": false, "isPaused": false, "judgmentMode": 1, "longNoteMode": 0, "lowestJudgmentConditionMode": 0, "multiplier": 8.470211182968008, "noteMobilityMode": 0, "noteModifyMode": 0, "noteSaltMode": 0, "point": 0.9881355932203391, "salt": 13844718, "stand": 949790}, {"audioMultiplier": 1.0, "autoMode": 0, "avatarID": "~76561198281660314", "avatarName": "PostScript", "band": 1003, "commentID": "954310e3a9f4ab0f7a0080b181fe53bad9d2553d3f37ed048661e39368dd346f1458943f39ff9b42db51ccec127ae66fdc2998980a1bda97eef8c6c9240508d8", "commentary": "", "date": "2025-05-19T13:13:33", "faintNoteMode": 0, "handled": 2, "hitPointsMode": 3, "inputFavorMode": 0, "inputFlags": 1, "isBand1": true, "isF": false, "isPaused": false, "judgmentMode": 1, "longNoteMode": 0, "lowestJudgmentConditionMode": 0, "multiplier": 6.427456647398844, "noteMobilityMode": 0, "noteModifyMode": 0, "noteSaltMode": 0, "point": 0.9935194416749752, "salt": 18925750, "stand": 948464}, {"audioMultiplier": 1.0, "autoMode": 0, "avatarID": "Jazy", "avatarName": "Jazy", "band": 994, "commentID": "34b0159f660e5eb3b90e398c3e68939d2b2421546e1bea34dbcc7337f6242e0875ba5d0eca50872ce2ea2a02c8f8cde2dc46e5481f8fd5e12734aa3461f6e5c4", "commentary": "", "date": "2025-10-24T00:22:13", "faintNoteMode": 0, "handled": 6, "hitPointsMode": 5, "inputFavorMode": 0, "inputFlags": 1, "isBand1": false, "isF": false, "isPaused": false, "judgmentMode": 4, "longNoteMode": 0, "lowestJudgmentConditionMode": 0, "multiplier": 12.329479768786127, "noteMobilityMode": 0, "noteModifyMode": 0, "noteSaltMode": 0, "point": 0.9910269192422737, "salt": 20885421, "stand": 947178}, {"audioMultiplier": 1.0, "autoMode": 0, "avatarID": "~76561198840362656", "avatarName": "미소녀돼서인생날먹", "band": 560, "commentID": "4c53bd59ee6452c798564995a20eb462e8b1d9814a330dbb07c9e5cff17f88cf4f6b5407a7abcb30c3131792b88341fa44e1425bd0737cfeb68a50a9933ab863", "commentary": "", "date": "2025-11-16T09:44:52", "faintNoteMode": 0, "handled": 1, "hitPointsMode": 1, "inputFavorMode": 0, "inputFlags": 1, "isBand1": false, "isF": false, "isPaused": false, "judgmentMode": 1, "longNoteMode": 0, "lowestJudgmentConditionMode": 0, "multiplier": 7.953757225433526, "noteMobilityMode": 0, "noteModifyMode": 0, "noteSaltMode": 0, "point": 0.9864406779661019, "salt": 431192734, "stand": 946510}, {"audioMultiplier": 1.0, "autoMode": 0, "avatarID": "~76561198994527774", "avatarName": "데이지", "band": 410, "commentID": "8c38a5bce3917e6c7449cfc2cb79cac9bd3ff8a4fe156d33d233c198d159d6f1b47734062bf88411990bb3dc52efa92648da3ace6d0d79603b08716933abcee1", "commentary": "", "date": "2025-11-12T12:46:30", "faintNoteMode": 0, "handled": 6, "hitPointsMode": 5, "inputFavorMode": 0, "inputFlags": 1, "isBand1": false, "isF": false, "isPaused": false, "judgmentMode": 1, "longNoteMode": 0, "lowestJudgmentConditionMode": 0, "multiplier": 8.032312138728326, "noteMobilityMode": 0, "noteModifyMode": 0, "noteSaltMode": 0, "point": 0.9830508474576276, "salt": 1244332468, "stand": 945812}, {"audioMultiplier": 1.0, "autoMode": 0, "avatarID": "perpel", "avatarName": "perpel", "band": 405, "commentID": "3129b35f04ed5befb2456d5fb3bb8c3ff6e26f63b530f1b9e23898091ea08a9cc265ab29f4f35c10aa7dc63b20d23fdb7a19cae569af30da65af521787f6bb41", "commentary": "", "date": "2024-12-24T16:17:17", "faintNoteMode": 0, "handled": 6, "hitPointsMode": 5, "inputFavorMode": 0, "inputFlags": 1, "isBand1": false, "isF": false, "isPaused": false, "judgmentMode": 1, "longNoteMode": 0, "lowestJudgmentConditionMode": 0, "multiplier": 7.903410404624277, "noteMobilityMode": 0, "noteModifyMode": 0, "noteSaltMode": 0, "point": 0.982751744765703, "salt": 706212734, "stand": 943409}, {"audioMultiplier": 1.0, "autoMode": 0, "avatarID": "gpkirootca1", "avatarName": "283", "band": 1003, "commentID": "6c85db588a3aed3a4188050bdd34434408e7f1a5b1234a955236d67e2f392fb964ca16ce680b56a97e29a1a2d86497e322c15dcf650f8fc45eee5917c3552cb4", "commentary": "", "date": "2026-06-16T08:49:31", "faintNoteMode": 0, "handled": 2, "hitPointsMode": 3, "inputFavorMode": 0, "inputFlags": 1, "isBand1": true, "isF": false, "isPaused": false, "judgmentMode": 1, "longNoteMode": 0, "lowestJudgmentConditionMode": 0, "multiplier": 8.670520231213873, "noteMobilityMode": 0, "noteModifyMode": 0, "noteSaltMode": 0, "point": 0.9906281156530408, "salt": 169853703, "stand": 940697}, {"audioMultiplier": 1.0, "autoMode": 0, "avatarID": "~76561198401372271", "avatarName": "Peaceful08", "band": 450, "commentID": "f7fcc2dc63594336def2e3fab0b9dfdb92d46d4fe263d382430978d0436ae7f7a29c4bfd96e8685dde4dea71776af249268697bb612df89ebd18e87f29aa4736", "commentary": "", "date": "2025-08-18T12:38:33", "faintNoteMode": 0, "handled": 6, "hitPointsMode": 5, "inputFavorMode": 0, "inputFlags": 1, "isBand1": false, "isF": false, "isPaused": false, "judgmentMode": 1, "longNoteMode": 0, "lowestJudgmentConditionMode": 0, "multiplier": 7.777167630057801, "noteMobilityMode": 0, "noteModifyMode": 0, "noteSaltMode": 0, "point": 0.9877367896311072, "salt": 171451875, "stand": 940089}, {"audioMultiplier": 1.0, "autoMode": 0, "avatarID": "cuneo1206", "avatarName": "Seori Batang", "band": 354, "commentID": "de89848ba0fca7543e83f3c94ee14ce27551ed8150379ee7d007321cec6e3c88095f54a506447a3a957f567ce8b9aa96c070a14bd05b2d796ca348a550bd3648", "commentary": "", "date": "2025-02-20T00:49:43", "faintNoteMode": 0, "handled": 6, "hitPointsMode": 5, "inputFavorMode": 0, "inputFlags": 1, "isBand1": false, "isF": false, "isPaused": false, "judgmentMode": 1, "longNoteMode": 0, "lowestJudgmentConditionMode": 0, "multiplier": 7.728323699421965, "noteMobilityMode": 0, "noteModifyMode": 0, "noteSaltMode": 0, "point": 0.9831505483549353, "salt": 5194312, "stand": 940029}, {"audioMultiplier": 1.0, "autoMode": 0, "avatarID": "~76561198886215446", "avatarName": "reaUga", "band": 216, "commentID": "0279c551269bf3148eaaba823cdc3fb65842533d9797ef38f1f6a5336b77ec5221a69ca8cb850dd857a06d800d6f378ef70bed435a7085d33746256ac789b38a", "commentary": "", "date": "2026-05-20T08:02:57", "faintNoteMode": 0, "handled": 6, "hitPointsMode": 5, "inputFavorMode": 0, "inputFlags": 1, "isBand1": false, "isF": false, "isPaused": false, "judgmentMode": 1, "longNoteMode": 0, "lowestJudgmentConditionMode": 0, "multiplier": 10.040462427745664, "noteMobilityMode": 0, "noteModifyMode": 0, "noteSaltMode": 0, "point": 0.9761477045908187, "salt": 548063171, "stand": 939890}, {"audioMultiplier": 1.0, "autoMode": 0, "avatarID": "~76561198969775749", "avatarName": "さえ", "band": 408, "commentID": "aaf95bc96c0efe63252a0208cae3376bedaf67bafd8ab6ce5b4a0503ad81d4bdab5213968d1fcaa0423be7725a375ef39a760162b37803d4b63d1aab2a0665bd", "commentary": "", "date": "2026-03-19T06:20:23", "faintNoteMode": 0, "handled": 1, "hitPointsMode": 1, "inputFavorMode": 0, "inputFlags": 1, "isBand1": false, "isF": false, "isPaused": false, "judgmentMode": 1, "longNoteMode": 0, "lowestJudgmentConditionMode": 0, "multiplier": 10.404624277456648, "noteMobilityMode": 0, "noteModifyMode": 0, "noteSaltMode": 0, "point": 0.9816550348953145, "salt": 502765859, "stand": 939252}, {"audioMultiplier": 1.5, "autoMode": 0, "avatarID": "~76561199290204252", "avatarName": "kkungkka", "band": 349, "commentID": "1a4f3b66676790fa7bc0161abdc4c42a39a407f37db9627d4b3c5b6def243c2dd483f36ece733665d254ad40999aa854999b6e3904769dd8630ba253eec513c1", "commentary": "1.5", "date": "2026-03-28T17:46:08", "faintNoteMode": 0, "handled": 6, "hitPointsMode": 5, "inputFavorMode": 0, "inputFlags": 1, "isBand1": false, "isF": false, "isPaused": false, "judgmentMode": 1, "longNoteMode": 0, "lowestJudgmentConditionMode": 0, "multiplier": 5.598458574181118, "noteMobilityMode": 0, "noteModifyMode": 0, "noteSaltMode": 1, "point": 0.9822532402791628, "salt": 14792500, "stand": 936510}, {"audioMultiplier": 1.0, "autoMode": 0, "avatarID": "tonggyegang", "avatarName": "EstLittera", "band": 433, "commentID": "5e2fe8f781f9b3244201cccd1215d18024847b8e64186327801c5fe113c9663926e9b468df3ec0fc8bb55915782e335886478d85c14cafa6a17015f783340635", "commentary": "", "date": "2024-11-24T14:59:53", "faintNoteMode": 0, "handled": 1, "hitPointsMode": 1, "inputFavorMode": 0, "inputFlags": 1, "isBand1": false, "isF": false, "isPaused": false, "judgmentMode": 1, "longNoteMode": 0, "lowestJudgmentConditionMode": 0, "multiplier": 5.953757225433526, "noteMobilityMode": 0, "noteModifyMode": 0, "noteSaltMode": 0, "point": 0.9847457627118644, "salt": 43479015, "stand": 936321}, {"audioMultiplier": 1.0, "autoMode": 0, "avatarID": "SafeHouse", "avatarName": "SafeHouse", "band": 860, "commentID": "49ede5f7ef2b4f4dd6978e21a7211534d2539a9f915d84cf607992c9d3ff458b619c77928487d9d5df91a5af9142b30ad911386c71b256fe41023578cbdbceac", "commentary": "", "date": "2024-10-06T04:31:10", "faintNoteMode": 0, "handled": 6, "hitPointsMode": 5, "inputFavorMode": 0, "inputFlags": 1, "isBand1": false, "isF": false, "isPaused": false, "judgmentMode": 1, "longNoteMode": 0, "lowestJudgmentConditionMode": 0, "multiplier": 7.283236994219653, "noteMobilityMode": 0, "noteModifyMode": 0, "noteSaltMode": 0, "point": 0.9832502492522438, "salt": 12372093, "stand": 933858}, {"audioMultiplier": 1.0, "autoMode": 0, "avatarID": "spehscolon", "avatarName": "Spehs", "band": 1003, "commentID": "1a6f9c6b6b1d0e0852b52acfc76879133f029b3d6bf1983b2fc059dec8af4c4dc35b68d7fd62c5a931b1560c5d08451abf4a87dc0ec5c976602bebab7c639a01", "commentary": "", "date": "2023-12-01T09:11:10", "faintNoteMode": 0, "handled": 2, "hitPointsMode": 5, "inputFavorMode": 0, "inputFlags": 1, "isBand1": true, "isF": false, "isPaused": false, "judgmentMode": 1, "longNoteMode": 0, "lowestJudgmentConditionMode": 0, "multiplier": 7.421965317919075, "noteMobilityMode": 0, "noteModifyMode": 0, "noteSaltMode": 0, "point": 0.9872382851445674, "salt": 1794491046, "stand": 931724}, {"audioMultiplier": 1.0, "autoMode": 0, "avatarID": "kfantabb", "avatarName": "Moon_Disaster", "band": 596, "commentID": "0e8f1f8215ae6846879813febddff446299b6301972672460f0e3eed8251c79b7f614cf0f0adffb831de6f30011aabc0386d2ec126af76451d7a475db273800a", "commentary": "", "date": "2025-09-20T19:17:49", "faintNoteMode": 0, "handled": 6, "hitPointsMode": 5, "inputFavorMode": 0, "inputFlags": 1, "isBand1": false, "isF": false, "isPaused": false, "judgmentMode": 1, "longNoteMode": 0, "lowestJudgmentConditionMode": 0, "multiplier": 8.430057803468209, "noteMobilityMode": 0, "noteModifyMode": 0, "noteSaltMode": 0, "point": 0.986726546906188, "salt": 17909812, "stand": 931126}, {"audioMultiplier": 1.0, "autoMode": 0, "avatarID": "~76561198185984233", "avatarName": "csk", "band": 779, "commentID": "a8478dcf15709e8751a520ff97ae2ae5db742f80b70da83e7e1e030c8e125bbfe68f495de910bbaa83d9c807b81edb6a5f03951645d99a374c778373f4b8e0e7", "commentary": "", "date": "2026-03-13T02:22:12", "faintNoteMode": 0, "handled": 6, "hitPointsMode": 5, "inputFavorMode": 0, "inputFlags": 1, "isBand1": false, "isF": false, "isPaused": false, "judgmentMode": 1, "longNoteMode": 0, "lowestJudgmentConditionMode": 0, "multiplier": 7.662427745664739, "noteMobilityMode": 0, "noteModifyMode": 0, "noteSaltMode": 0, "point": 0.9840478564307084, "salt": 116835625, "stand": 930209}, {"audioMultiplier": 1.0, "autoMode": 0, "avatarID": "~76561198163545274", "avatarName": "김융털", "band": 320, "commentID": "c86c4dfc8ea7d145d2a8665c7d0726834cbea7c2fa70e869122077787dd38a48cd9831358b304a6626f17ce2acf5cb8804c89e763d5e414305a3bb4936bd6a35", "commentary": "", "date": "2025-11-26T17:46:52", "faintNoteMode": 0, "handled": 6, "hitPointsMode": 5, "inputFavorMode": 0, "inputFlags": 1, "isBand1": false, "isF": false, "isPaused": false, "judgmentMode": 1, "longNoteMode": 0, "lowestJudgmentConditionMode": 0, "multiplier": 8.196531791907514, "noteMobilityMode": 0, "noteModifyMode": 0, "noteSaltMode": 0, "point": 0.9765702891326027, "salt": 1559468, "stand": 929491}, {"audioMultiplier": 1.0, "autoMode": 0, "avatarID": "pkrk50", "avatarName": "민트초코치즈치킨", "band": 894, "commentID": "0058b8d52aa5b373644c64b769543461c81e68741dfc19e83b3716ec3e785eac85bc1d6c96b01f6ea632f69f4488012271275c3ebe1d7bedf18b7d214b8adfb0", "commentary": "", "date": "2025-02-16T14:36:49", "faintNoteMode": 0, "handled": 1, "hitPointsMode": 1, "inputFavorMode": 0, "inputFlags": 1, "isBand1": false, "isF": false, "isPaused": false, "judgmentMode": 2, "longNoteMode": 0, "lowestJudgmentConditionMode": 0, "multiplier": 8.676300578034683, "noteMobilityMode": 0, "noteModifyMode": 0, "noteSaltMode": 0, "point": 0.9838484546360928, "salt": 294961453, "stand": 928424}, {"audioMultiplier": 1.0, "autoMode": 0, "avatarID": "weedgod", "avatarName": "Yusaki", "band": 808, "commentID": "041d6a27675140819cd5e015050fb0de1bb734be24844229cb31687fa258db2bf429a7467aa56238fd96c17597dfa86d1c91f7019e999893b6e62ccc7bc5a4e8", "commentary": "", "date": "2025-02-16T09:48:49", "faintNoteMode": 0, "handled": 6, "hitPointsMode": 5, "inputFavorMode": 0, "inputFlags": 1, "isBand1": false, "isF": false, "isPaused": false, "judgmentMode": 1, "longNoteMode": 0, "lowestJudgmentConditionMode": 0, "multiplier": 9.212543352601156, "noteMobilityMode": 0, "noteModifyMode": 0, "noteSaltMode": 0, "point": 0.9882352941176474, "salt": 96837203, "stand": 927846}, {"audioMultiplier": 1.0, "autoMode": 0, "avatarID": "superhr1234", "avatarName": "쪽파아줌마", "band": 190, "commentID": "1b390c561f04600bc67ceba97f3cc16a6016f761ea6a4b6a6c8eedc7d0b33a124e5a3c840cc60275414c142903d1b32fa9209c9c95427a28d73d9467ab55b256", "commentary": "", "date": "2025-01-14T04:24:09", "faintNoteMode": 0, "handled": 5, "hitPointsMode": 2, "inputFavorMode": 0, "inputFlags": 1, "isBand1": false, "isF": false, "isPaused": true, "judgmentMode": 1, "longNoteMode": 0, "lowestJudgmentConditionMode": 0, "multiplier": 8.092485549132949, "noteMobilityMode": 0, "noteModifyMode": 0, "noteSaltMode": 0, "point": 0.9686626746506992, "salt": 4416937, "stand": 923349}, {"audioMultiplier": 1.0, "autoMode": 0, "avatarID": "~76561198840907721", "avatarName": "lkl", "band": 335, "commentID": "9de0e669b559317c6ae0c887a3dceb87eac5261658ae7cfd80f53a5d9ddaacfc535e5e6eceb0b510602f75f41dd3e7517e8c86b20d17c1e6cc75f9a0b1c1542d", "commentary": "", "date": "2026-03-03T00:08:23", "faintNoteMode": 0, "handled": 6, "hitPointsMode": 5, "inputFavorMode": 0, "inputFlags": 1, "isBand1": false, "isF": false, "isPaused": false, "judgmentMode": 1, "longNoteMode": 0, "lowestJudgmentConditionMode": 0, "multiplier": 6.55664739884393, "noteMobilityMode": 0, "noteModifyMode": 0, "noteSaltMode": 0, "point": 0.9773678963110671, "salt": 6383953, "stand": 923100}, {"audioMultiplier": 1.0, "autoMode": 0, "avatarID": "_sier333", "avatarName": "sier", "band": 373, "commentID": "3432c15c7a6f01bd71ff2868a35fafeed739c9c36b0f0cc38ebe4671982503c355d4e48aa67f6749bd7f2c9f8df6f8ef54173bd1bc1bcbd4963e11c1a8c10320", "commentary": "", "date": "2023-12-18T22:58:18", "faintNoteMode": 0, "handled": 6, "hitPointsMode": 5, "inputFavorMode": 0, "inputFlags": 1, "isBand1": false, "isF": false, "isPaused": false, "judgmentMode": 1, "longNoteMode": 0, "lowestJudgmentConditionMode": 0, "multiplier": 6.531791907514451, "noteMobilityMode": 0, "noteModifyMode": 0, "noteSaltMode": 0, "point": 0.9755732801595217, "salt": 321012406, "stand": 920289}, {"audioMultiplier": 1.0, "autoMode": 0, "avatarID": "~76561198088664063", "avatarName": "Nighthom", "band": 444, "commentID": "7187113ee90962246df08d454a733550dcb720bb0ba98e298db0674f6e175ed4a152d1aa04d951289aa408b39fbb8c3eec759256ef282e3e3b8b40c7ccc43d7c", "commentary": "", "date": "2025-12-04T12:21:54", "faintNoteMode": 0, "handled": 6, "hitPointsMode": 5, "inputFavorMode": 0, "inputFlags": 1, "isBand1": false, "isF": false, "isPaused": false, "judgmentMode": 2, "longNoteMode": 0, "lowestJudgmentConditionMode": 0, "multiplier": 8.196531791907514, "noteMobilityMode": 0, "noteModifyMode": 0, "noteSaltMode": 0, "point": 0.9801595214356935, "salt": 33418750, "stand": 911525}, {"audioMultiplier": 1.0, "autoMode": 0, "avatarID": "~76561198217782603", "avatarName": "sak", "band": 891, "commentID": "63a19ee9d6a67c60b3c3e9f580f3b406f8ec1b4ace47bb34f2ea967c5bbf3dd8a33cdcbf17a93e1a2fc08d7ee7f555d4074e9c1fe23b1a1d87172672b499a25b", "commentary": "", "date": "2026-05-23T18:52:14", "faintNoteMode": 0, "handled": 5, "hitPointsMode": 2, "inputFavorMode": 0, "inputFlags": 1, "isBand1": false, "isF": false, "isPaused": false, "judgmentMode": 1, "longNoteMode": 0, "lowestJudgmentConditionMode": 0, "multiplier": 9.439306358381502, "noteMobilityMode": 0, "noteModifyMode": 0, "noteSaltMode": 0, "point": 0.9788634097706883, "salt": 177674484, "stand": 911146}, {"audioMultiplier": 1.0, "autoMode": 0, "avatarID": "onestar9958", "avatarName": "RinaeBelle", "band": 543, "commentID": "64cdbd7dbf742b1a53b5a055480732f93903d670e74745e3441a760e4ac227ec5c7e10ccf73759bcd29c5664a1478187caeb4bba375028146a2ae83dcd8d6ffb", "commentary": "", "date": "2024-12-08T13:07:42", "faintNoteMode": 0, "handled": 1, "hitPointsMode": 1, "inputFavorMode": 0, "inputFlags": 1, "isBand1": false, "isF": false, "isPaused": false, "judgmentMode": 1, "longNoteMode": 0, "lowestJudgmentConditionMode": 0, "multiplier": 5.993595375722544, "noteMobilityMode": 0, "noteModifyMode": 0, "noteSaltMode": 0, "point": 0.9669990029910275, "salt": 104916515, "stand": 910169}, {"audioMultiplier": 1.0, "autoMode": 0, "avatarID": "Moose", "avatarName": "무스", "band": 1003, "commentID": "71d2e3e6e603052640503406824546f4fcbdf414b2293f54ef94e783a0fff835f0217d4831193d47e88ec513e911bb38664b8f4c8e3a1a907262adc39aab4161", "commentary": "", "date": "2025-11-29T09:05:35", "faintNoteMode": 0, "handled": 2, "hitPointsMode": 3, "inputFavorMode": 0, "inputFlags": 1, "isBand1": true, "isF": false, "isPaused": false, "judgmentMode": 1, "longNoteMode": 0, "lowestJudgmentConditionMode": 0, "multiplier": 8.196531791907514, "noteMobilityMode": 0, "noteModifyMode": 0, "noteSaltMode": 0, "point": 0.9808574277168498, "salt": 14559890, "stand": 908334}, {"audioMultiplier": 1.0, "autoMode": 0, "avatarID": "~76561199833502204", "avatarName": "DEN1MhΛTΣR", "band": 270, "commentID": "e95ab65d5a7d39fb264fc409a85d43cb068afa2037de3c1ee5115cad818ef1cc4a160b933e79e7ba967da40d7e42c8f590261033f79ad504d22985fe324013d8", "commentary": "", "date": "2026-05-02T14:27:36", "faintNoteMode": 0, "handled": 1, "hitPointsMode": 1, "inputFavorMode": 0, "inputFlags": 1, "isBand1": false, "isF": false, "isPaused": false, "judgmentMode": 1, "longNoteMode": 0, "lowestJudgmentConditionMode": 0, "multiplier": 6.936416184971098, "noteMobilityMode": 0, "noteModifyMode": 0, "noteSaltMode": 0, "point": 0.9700897308075779, "salt": 45841156, "stand": 907427}, {"audioMultiplier": 1.0, "autoMode": 1, "avatarID": "wilydodo", "avatarName": "WILYDODO", "band": 286, "commentID": "3c945e603440086ad85b8c64c1e41cdbd30516e2642aeff73ac9d61ee7e4cb1a65b33a033fce6e54e0d8328916e61ed8bf8b7f9786232907a1e730eb36f14f34", "commentary": "", "date": "2025-11-08T03:09:12", "faintNoteMode": 0, "handled": 6, "hitPointsMode": 5, "inputFavorMode": 0, "inputFlags": 1, "isBand1": false, "isF": false, "isPaused": false, "judgmentMode": 1, "longNoteMode": 0, "lowestJudgmentConditionMode": 0, "multiplier": 4.959537572254336, "noteMobilityMode": 0, "noteModifyMode": 0, "noteSaltMode": 1, "point": 0.9705882352941185, "salt": 2356312, "stand": 905214}, {"audioMultiplier": 1.0, "autoMode": 0, "avatarID": "~76561198860332699", "avatarName": "꾸꾸", "band": 318, "commentID": "3851fca43a807030bb1bcce0a64711e620c6603cc2182f318c68b00ea7419f0202b125cc9728c3fabd17dd51a4843b257a2c89422461001bf92216a6796d9da8", "commentary": "", "date": "2025-07-09T16:03:01", "faintNoteMode": 0, "handled": 6, "hitPointsMode": 5, "inputFavorMode": 0, "inputFlags": 1, "isBand1": false, "isF": false, "isPaused": false, "judgmentMode": 1, "longNoteMode": 0, "lowestJudgmentConditionMode": 0, "multiplier": 8.375722543352602, "noteMobilityMode": 0, "noteModifyMode": 0, "noteSaltMode": 0, "point": 0.9765702891326027, "salt": 455168609, "stand": 904516}, {"audioMultiplier": 1.0, "autoMode": 0, "avatarID": "nk801880", "avatarName": "넥스스", "band": 497, "commentID": "8cabd2d7e607748ab0e0c5aae6dbd3a02cfe6559b19220643187a539b79d66f6ddd0b5a99d0c3c815a3e7b70ad8dc2622cf4c71e772b2d7a2de1ed64b749bd34", "commentary": "", "date": "2024-01-26T06:21:42", "faintNoteMode": 0, "handled": 6, "hitPointsMode": 5, "inputFavorMode": 0, "inputFlags": 1, "isBand1": false, "isF": false, "isPaused": false, "judgmentMode": 2, "longNoteMode": 0, "lowestJudgmentConditionMode": 0, "multiplier": 8.874971098265895, "noteMobilityMode": 0, "noteModifyMode": 0, "noteSaltMode": 0, "point": 0.9746759720837495, "salt": 5829515, "stand": 904416}, {"audioMultiplier": 1.0, "autoMode": 0, "avatarID": "rubendia12", "avatarName": "루벤디아", "band": 399, "commentID": "276c9c6df584f0d7a55d62b255116de208fcebf9ae98ee300fac7af5113b8c4335589164d184a1e037191461f2776fe0dd5c083075efecfa182b3d3a87da8717", "commentary": "", "date": "2025-07-26T07:53:57", "faintNoteMode": 0, "handled": 6, "hitPointsMode": 5, "inputFavorMode": 0, "inputFlags": 1, "isBand1": false, "isF": false, "isPaused": false, "judgmentMode": 1, "longNoteMode": 0, "lowestJudgmentConditionMode": 0, "multiplier": 9.53757225433526, "noteMobilityMode": 0, "noteModifyMode": 0, "noteSaltMode": 0, "point": 0.9716849451645073, "salt": 6336578, "stand": 904017}, {"audioMultiplier": 1.0, "autoMode": 0, "avatarID": "dleodus33", "avatarName": "heckt", "band": 442, "commentID": "2f118486b12d748dbb3d7fe9304a9c917a241b7a86cc357e8d5c4bdb773ae0074ee015e256725d84b080c69caa8d322d768d8b80ddf73bd1363327679d151fb3", "commentary": "", "date": "2024-04-03T10:26:23", "faintNoteMode": 0, "handled": 6, "hitPointsMode": 5, "inputFavorMode": 0, "inputFlags": 1, "isBand1": false, "isF": false, "isPaused": false, "judgmentMode": 1, "longNoteMode": 0, "lowestJudgmentConditionMode": 0, "multiplier": 6.936416184971098, "noteMobilityMode": 0, "noteModifyMode": 0, "noteSaltMode": 0, "point": 0.9693918245264223, "salt": 1408140, "stand": 885722}, {"audioMultiplier": 1.0, "autoMode": 0, "avatarID": "~76561198387805910", "avatarName": "Jhin", "band": 232, "commentID": "450010a0ae63cc0b1024cdc93b0d9648b0a215a9b7cd04662a76088efc4a5694482edf50508cdb03642943e28931d53bbe3672c729499c5799d45803e972fa7d", "commentary": "", "date": "2026-05-21T12:29:55", "faintNoteMode": 0, "handled": 6, "hitPointsMode": 5, "inputFavorMode": 0, "inputFlags": 1, "isBand1": false, "isF": false, "isPaused": false, "judgmentMode": 1, "longNoteMode": 0, "lowestJudgmentConditionMode": 0, "multiplier": 10.693641618497109, "noteMobilityMode": 0, "noteModifyMode": 0, "noteSaltMode": 0, "point": 0.9539920159680644, "salt": 277973203, "stand": 883090}, {"audioMultiplier": 1.0, "autoMode": 0, "avatarID": "Hyunwol", "avatarName": "Hyunwol", "band": 503, "commentID": "13f5f028d1e1bedf6c4356c236181acdde33519c11d80d61bc788cf6d94a13cb96231d2f6bd68c00423bfcc2b677bf241d3aab2d7a7272a4b8012f8489bcf035", "commentary": "", "date": "2025-03-08T10:36:50", "faintNoteMode": 0, "handled": 6, "hitPointsMode": 5, "inputFavorMode": 0, "inputFlags": 1, "isBand1": false, "isF": false, "isPaused": false, "judgmentMode": 1, "longNoteMode": 0, "lowestJudgmentConditionMode": 0, "multiplier": 7.664739884393064, "noteMobilityMode": 0, "noteModifyMode": 0, "noteSaltMode": 0, "point": 0.971884346959124, "salt": 65974203, "stand": 878913}, {"audioMultiplier": 1.0, "autoMode": 0, "avatarID": "rnjswldn1003", "avatarName": "mintchocolate", "band": 158, "commentID": "e1c951ce98468af994e016fc429a9eb2eee6be7bc939bb46917d78d60ebcafd33d7aa58dbb040c5fb2ee7cbbdfdbeaa03960603acc42887b1b327b851933958b", "commentary": "", "date": "2024-10-19T04:10:17", "faintNoteMode": 0, "handled": 1, "hitPointsMode": 1, "inputFavorMode": 0, "inputFlags": 1, "isBand1": false, "isF": false, "isPaused": false, "judgmentMode": 1, "longNoteMode": 0, "lowestJudgmentConditionMode": 0, "multiplier": 7.486358381502891, "noteMobilityMode": 0, "noteModifyMode": 0, "noteSaltMode": 0, "point": 0.9478564307078768, "salt": 34787968, "stand": 873190}, {"audioMultiplier": 1.0, "autoMode": 0, "avatarID": "~76561198303937043", "avatarName": "mochi", "band": 336, "commentID": "6b30de6c038efbb7a13b1bb1a62d921a372f4d370525a7de777bbe427ecb7a8ab950f4fb7a2dcd12a98773f3020b9c79bb0ea09048768c5d822c97628bcb6ff3", "commentary": "", "date": "2026-02-11T07:48:11", "faintNoteMode": 0, "handled": 6, "hitPointsMode": 5, "inputFavorMode": 0, "inputFlags": 1, "isBand1": false, "isF": false, "isPaused": false, "judgmentMode": 1, "longNoteMode": 0, "lowestJudgmentConditionMode": 0, "multiplier": 6.445086705202312, "noteMobilityMode": 0, "noteModifyMode": 0, "noteSaltMode": 0, "point": 0.9587238285144577, "salt": 129521140, "stand": 872592}, {"audioMultiplier": 1.0, "autoMode": 0, "avatarID": "jinu1276", "avatarName": "BF", "band": 400, "commentID": "50033503a8a3660efbb803d5c70d0c5a62c6df0033e8e881ff39fa3e36cc9fa0797e8d8b0c4eb0ad216015046304c14167bdec3a99a1e8d7fab72fb6c6981f6b", "commentary": "", "date": "2024-06-15T04:34:31", "faintNoteMode": 0, "handled": 5, "hitPointsMode": 2, "inputFavorMode": 0, "inputFlags": 1, "isBand1": false, "isF": false, "isPaused": false, "judgmentMode": 1, "longNoteMode": 0, "lowestJudgmentConditionMode": 0, "multiplier": 4.054913294797688, "noteMobilityMode": 0, "noteModifyMode": 0, "noteSaltMode": 0, "point": 0.9465603190428725, "salt": 13503062, "stand": 858354}, {"audioMultiplier": 1.0, "autoMode": 0, "avatarID": "~76561199233371426", "avatarName": "댕라", "band": 294, "commentID": "7120885b8d02ad86b36cf44efd21f35f00cd8d617756c80de76848c04e0253c258ba4191733cedb12aa9891f277f81c5638fd6864492f2b4cdfb8621145932dd", "commentary": "", "date": "2026-01-11T09:06:30", "faintNoteMode": 0, "handled": 6, "hitPointsMode": 5, "inputFavorMode": 0, "inputFlags": 1, "isBand1": false, "isF": false, "isPaused": false, "judgmentMode": 1, "longNoteMode": 0, "lowestJudgmentConditionMode": 0, "multiplier": 7.91907514450867, "noteMobilityMode": 0, "noteModifyMode": 0, "noteSaltMode": 0, "point": 0.9408773678963119, "salt": 380053953, "stand": 836041}, {"audioMultiplier": 1.0, "autoMode": 0, "avatarID": "~76561198372919972", "avatarName": "Arai", "band": 778, "commentID": "adc8fd06eec4381b1e0fc4030c1022c9df751bd148576ec99fa9133cbefffcfe7b3447811036638eedd8a842cde9cc591dd84b94f4b563b65b17bcd123f4e5f7", "commentary": "", "date": "2026-03-28T18:42:17", "faintNoteMode": 0, "handled": 6, "hitPointsMode": 5, "inputFavorMode": 0, "inputFlags": 1, "isBand1": false, "isF": false, "isPaused": false, "judgmentMode": 1, "longNoteMode": 0, "lowestJudgmentConditionMode": 0, "multiplier": 7.91907514450867, "noteMobilityMode": 0, "noteModifyMode": 0, "noteSaltMode": 0, "point": 0.9586241276171502, "salt": 41573078, "stand": 834317}, {"audioMultiplier": 1.0, "autoMode": 0, "avatarID": "lem0ner42", "avatarName": "lem0ner42", "band": 462, "commentID": "8905d9ff18c251674c03137a218b4135e48be0f36e9626199058e2ceb98a2aba3998546a06a69eee7f6e371181dc97d5d57ad42bada7e8dbcc0630e86dceecae", "commentary": "", "date": "2024-04-13T11:41:51", "faintNoteMode": 0, "handled": 6, "hitPointsMode": 5, "inputFavorMode": 0, "inputFlags": 1, "isBand1": false, "isF": false, "isPaused": false, "judgmentMode": 4, "longNoteMode": 0, "lowestJudgmentConditionMode": 0, "multiplier": 8.38150289017341, "noteMobilityMode": 0, "noteModifyMode": 0, "noteSaltMode": 0, "point": 0.9461615154536411, "salt": 882546, "stand": 824735}, {"audioMultiplier": 1.0, "autoMode": 0, "avatarID": "~76561198314713849", "avatarName": "dlldlll", "band": 237, "commentID": "a34a5ecff97de5e67ec31e23e43f860076fe43d7b0ab3c63115023e92474b503d60ade6428828b37e148a1641a4f4e30fc5d7c48007cab2c31a09688aa7bb943", "commentary": "", "date": "2025-11-10T03:54:24", "faintNoteMode": 0, "handled": 5, "hitPointsMode": 2, "inputFavorMode": 0, "inputFlags": 1, "isBand1": false, "isF": false, "isPaused": false, "judgmentMode": 1, "longNoteMode": 0, "lowestJudgmentConditionMode": 0, "multiplier": 7.803468208092486, "noteMobilityMode": 0, "noteModifyMode": 0, "noteSaltMode": 0, "point": 0.9286141575274186, "salt": 2137156, "stand": 824516}, {"audioMultiplier": 1.0, "autoMode": 0, "avatarID": "Cra_Dow", "avatarName": "CraDow", "band": 329, "commentID": "b790d60c2f6e51cdeaa173101165560ebd14a306d0cb4489f22d9b3bea40944b8d4f7333ab56e18bb0e8b9a03d5cef06cdf44ee1f5361213f1d3f852a9f03533", "commentary": "", "date": "2024-07-25T18:05:14", "faintNoteMode": 0, "handled": 5, "hitPointsMode": 2, "inputFavorMode": 0, "inputFlags": 1, "isBand1": false, "isF": false, "isPaused": false, "judgmentMode": 2, "longNoteMode": 0, "lowestJudgmentConditionMode": 0, "multiplier": 11.716763005780347, "noteMobilityMode": 0, "noteModifyMode": 0, "noteSaltMode": 11, "point": 0.9241276171485548, "salt": 33611296, "stand": 815623}, {"audioMultiplier": 1.0, "autoMode": 1, "avatarID": "~76561199352314474", "avatarName": "go yang I", "band": 386, "commentID": "7a09b35949cf165ecefe43327738c54f52ac4a216731626dfed44b762f5a1f4a40e0e2284828bbb4cb3981910df8563c71f16dad14e37235550be4c40dae8f1b", "commentary": "", "date": "2026-02-18T12:30:53", "faintNoteMode": 0, "handled": 5, "hitPointsMode": 2, "inputFavorMode": 0, "inputFlags": 1, "isBand1": false, "isF": false, "isPaused": false, "judgmentMode": 4, "longNoteMode": 0, "lowestJudgmentConditionMode": 0, "multiplier": 8.473179190751445, "noteMobilityMode": 0, "noteModifyMode": 0, "noteSaltMode": 0, "point": 0.9317682317682331, "salt": 37062578, "stand": 805922}, {"audioMultiplier": 1.0, "autoMode": 0, "avatarID": "~76561198149949188", "avatarName": "FIRE", "band": 149, "commentID": "5ee290041aa0c2caa07812cf59dbddd17efd5def416feed5b3ac884855e787697b884b92a8e57cb7ec2478959591e89039a03ad69209f72febc2c607e962f13a", "commentary": "", "date": "2025-12-08T13:17:42", "faintNoteMode": 0, "handled": 1, "hitPointsMode": 1, "inputFavorMode": 0, "inputFlags": 1, "isBand1": false, "isF": false, "isPaused": false, "judgmentMode": 1, "longNoteMode": 0, "lowestJudgmentConditionMode": 0, "multiplier": 7.8627745664739885, "noteMobilityMode": 0, "noteModifyMode": 0, "noteSaltMode": 0, "point": 0.8930139720558901, "salt": 529371250, "stand": 737557}, {"audioMultiplier": 1.0, "autoMode": 0, "avatarID": "~76561197982822345", "avatarName": "vmgod", "band": 187, "commentID": "ffc0efde603d070fdf10300a3a8951d86aaa19f8f20c60b1c4bd0470e1c87647acb39ec946364e75ba2e499bcb2e6a883a696ab9650b616bfef8d72332a7c794", "commentary": "", "date": "2025-06-09T15:12:04", "faintNoteMode": 0, "handled": 5, "hitPointsMode": 2, "inputFavorMode": 0, "inputFlags": 1, "isBand1": false, "isF": false, "isPaused": false, "judgmentMode": 1, "longNoteMode": 0, "lowestJudgmentConditionMode": 0, "multiplier": 7.373144508670521, "noteMobilityMode": 0, "noteModifyMode": 0, "noteSaltMode": 0, "point": 0.872954091816368, "salt": 10569234, "stand": 710498}, {"audioMultiplier": 1.0, "autoMode": 0, "avatarID": "~76561198150909675", "avatarName": "kirisame", "band": 244, "commentID": "48c8355662e1714cd175bbaebee996afd519eb25d47a2a02464e68ed6c4772ae82388db732a266e2922c1f59ea1f06515d7a44679f3823b346456ffb78430547", "commentary": "", "date": "2026-03-25T14:18:28", "faintNoteMode": 0, "handled": 1, "hitPointsMode": 1, "inputFavorMode": 0, "inputFlags": 1, "isBand1": false, "isF": false, "isPaused": false, "judgmentMode": 1, "longNoteMode": 0, "lowestJudgmentConditionMode": 0, "multiplier": 7.994219653179191, "noteMobilityMode": 0, "noteModifyMode": 0, "noteSaltMode": 0, "point": 0.8566301096709888, "salt": 108476953, "stand": 680159}, {"audioMultiplier": 1.0, "autoMode": 0, "avatarID": "~76561198852953473", "avatarName": "fhfhaa", "band": 160, "commentID": "8a9aa8094197e15c954421fc1f4f6d5db323ec42597d5c387518bb686f413fe3a882287dbe38c11ed929d147eb6852245aa0afe5664af004acf5939eb7f53a52", "commentary": "", "date": "2026-04-29T13:21:51", "faintNoteMode": 0, "handled": 1, "hitPointsMode": 1, "inputFavorMode": 0, "inputFlags": 1, "isBand1": false, "isF": false, "isPaused": false, "judgmentMode": 1, "longNoteMode": 0, "lowestJudgmentConditionMode": 0, "multiplier": 6.173410404624278, "noteMobilityMode": 0, "noteModifyMode": 0, "noteSaltMode": 0, "point": 0.8064870259481051, "salt": 9395984, "stand": 593509}, {"audioMultiplier": 1.03, "autoMode": 0, "avatarID": "~76561199869758340", "avatarName": "smdjdkdkdk", "band": 127, "commentID": "b95bf7b183930df00f18a40fe153e54761b16cb5308abc8034f7a805ab4df177b800986f6807d9f9a6b851e6dadfe4ca660f1acb49a0155bedc52a5090c91ccb", "commentary": "", "date": "2025-11-26T14:05:32", "faintNoteMode": 0, "handled": 7, "hitPointsMode": 4, "inputFavorMode": 0, "inputFlags": 1, "isBand1": false, "isF": false, "isPaused": false, "judgmentMode": 1, "longNoteMode": 0, "lowestJudgmentConditionMode": 0, "multiplier": 6.400977608171048, "noteMobilityMode": 0, "noteModifyMode": 0, "noteSaltMode": 0, "point": 0.9167167167167176, "salt": 4290312, "stand": 198387}, {"audioMultiplier": 1.0, "autoMode": 0, "avatarID": "~76561198043808773", "avatarName": "MCT", "band": 119, "commentID": "eda2046e8cef4d7a057dbead0f980c97b51eff59d7da3588578794526ecc0a49961d41f09b2b55379f2769dcfbe762aba0985020a98912292821daa2b07d3ae9", "commentary": "", "date": "2026-03-04T02:48:46", "faintNoteMode": 0, "handled": 4, "hitPointsMode": 1, "inputFavorMode": 0, "inputFlags": 1, "isBand1": false, "isF": true, "isPaused": false, "judgmentMode": 1, "longNoteMode": 0, "lowestJudgmentConditionMode": 0, "multiplier": 6.729248554913295, "noteMobilityMode": 0, "noteModifyMode": 0, "noteSaltMode": 0, "point": 0.8024344569288377, "salt": 282763875, "stand": 330189}], "favor": false, "standMe": 0, "totalComments": 115, "totalFavor": 1}